Workbook
Name EnvasadoFrascos: #REF!
Name EnvasadoFrascos: #REF!
Name EnvasadoFrascos: #REF!
Name EnvasadoFrascos: #REF!
Name EnvasadoFrascos: #REF!

Sheet Ternum tubos
B2: Datos
B3: Cliente | C3: TERNUM
B4: Producto
B5: Servicio | C5: Envasado
B6: Materiales Lab. Coper
B7: Envase | C7: Ovales | D7: Ovales | E7: Ovales | F7: Ovales | G7: Airless | H7: Airless
B8: Capacidad envase (ml): | C8: 50 | D8: 50 | E8: 100 | F8: 100 | G8: 50 | H8: 50
B9: Unidades | C9: 5000 | D9: 10000 | E9: 5000 | F9: 10000 | G9: 5000 | H9: 10000 | J9: Comentarios
B12: MO Planta Jumsa
B14: Tasa €/hora | C14: =+'BD tasas y precios'!$C$12 -> 32.2 | D14: =+'BD tasas y precios'!$C$12 -> 32.2 | E14: =+'BD tasas y precios'!$C$12 -> 32.2 | F14: =+'BD tasas y precios'!$C$12 -> 32.2 | G14: =+'BD tasas y precios'!$C$12 -> 32.2 | H14: =+'BD tasas y precios'!$C$12 -> 32.2
B16: Operación | C16: Envasado Tubo | D16: Envasado Tubo | E16: Envasado Tubo | F16: Envasado Tubo | G16: Envasado Tubo | H16: Envasado Tubo | J16: Si son 9K uds se buscar en el rango 5 k a 10 k
B17: Tiempo (horas) | C17: n.d. | D17: n.d. | E17: n.d. | F17: n.d. | G17: n.d. | H17: n.d. | J17: Sin tiempos ver tarifa directamente
B18: Tiempo (uds /hora) | C18: n.d. | D18: n.d. | E18: n.d. | F18: n.d. | G18: n.d. | H18: n.d. | J18: Los tubos no hay trazabilidad de formulas - entiendo que es mismo €/hora
B19: Unidad de referencia | C19: n.a. | D19: n.a. | E19: n.a. | F19: n.a. | G19: n.a. | H19: n.a.
B20: Personas | C20: 0 | D20: 0 | E20: 0 | F20: 0 | G20: 0 | H20: 0
B21: Tiempo (horas) | C21: n.a. | D21: n.a. | E21: n.a. | F21: n.a. | G21: n.a. | H21: n.a.
B22: €/ud tubo | C22: 0.1624 | D22: 0.1624 | E22: 0.168 | F22: 0.1554 | G22: 0.116 | H22: 0.104 | J22: El ultimo airless me da 105 , no es material
B23: Total (€/ ud) | C23: =+IF(C20>0,C22*1.85,C22) -> 0.1624 | D23: 0.146 | E23: =+IF(E20>0,E22*1.85,E22) -> 0.168 | F23: =+IF(F20>0,F22*1.85,F22) -> 0.1554 | G23: =+IF(G20>0,G22*1.85,G22) -> 0.116 | H23: =+IF(H20>0,H22*1.85,H22) -> 0.104
B25: Operación | C25: Envasado Estándar | D25: Envasado Estándar | E25: Envasado Estándar | F25: Envasado Estándar | G25: Envasado Estándar | H25: Envasado Estándar
B26: Tiempo (horas)
B27: Tiempo (uds /hora)
B28: Unidad de referencia
B29: Personas
B30: Tiempo (horas) | C30: =+IFERROR(IF(C26>0,C26*C29,C28/C27*C29),"") | D30: =+IFERROR(IF(D26>0,D26*D29,D28/D27*D29),"") | E30: =+IFERROR(IF(E26>0,E26*E29,E28/E27*E29),"") | F30: =+IFERROR(IF(F26>0,F26*F29,F28/F27*F29),"") | G30: =+IFERROR(IF(G26>0,G26*G29,G28/G27*G29),"") | H30: =+IFERROR(IF(H26>0,H26*H29,H28/H27*H29),"")
B31: €/ud tubo
B32: Total (€/ ud) | C32: =+IFERROR(($C$14*C30)/C9,"") | D32: =+IFERROR(($C$14*D30)/D9,"") | E32: =+IFERROR(($C$14*E30)/E9,"") | F32: =+IFERROR(($C$14*F30)/F9,"") | G32: =+IFERROR(($C$14*G30)/G9,"") | H32: =+IFERROR(($C$14*H30)/H9,"")
B34: Operación | C34: Estuchado | D34: Estuchado | E34: Estuchado | F34: Estuchado | G34: Estuchado | H34: Estuchado
B35: Tiempo (horas)
B36: Tiempo (uds /hora)
B37: Unidad de referencia
B38: Personas
B39: Tiempo (horas) | C39: =+IFERROR(IF(C35>0,C35*C38,C37/C36*C38),"") | D39: =+IFERROR(IF(D35>0,D35*D38,D37/D36*D38),"") | E39: =+IFERROR(IF(E35>0,E35*E38,E37/E36*E38),"") | F39: =+IFERROR(IF(F35>0,F35*F38,F37/F36*F38),"")
B40: €/ud tubo
B41: Total (€/ ud) | C41: =+IFERROR(($C$14*C39)/C9,"") | D41: =+IFERROR(($C$14*D39)/D9,"") | E41: =+IFERROR(($C$14*E39)/E9,"") | F41: =+IFERROR(($C$14*F39)/F9,"")
B43: Operación | C43: Env. + Est. | D43: Env. + Est. | E43: Env. + Est. | F43: Env. + Est. | G43: Env. + Est. | H43: Env. + Est.
B44: Tiempo (horas)
B45: Tiempo (uds /hora)
B46: Unidad de referencia
B47: Personas
B48: Tiempo (horas) | C48: =+IFERROR(IF(C44>0,C44*C47,C46/C45*C47),"") | D48: =+IFERROR(IF(D44>0,D44*D47,D46/D45*D47),"") | E48: =+IFERROR(IF(E44>0,E44*E47,E46/E45*E47),"") | F48: =+IFERROR(IF(F44>0,F44*F47,F46/F45*F47),"")
B49: €/ud tubo
B50: Total (€/ ud) | C50: =+IFERROR(($C$14*C48)/C9,"") | D50: =+IFERROR(($C$14*D48)/D9,"") | E50: =+IFERROR(($C$14*E48)/E9,"") | F50: =+IFERROR(($C$14*F48)/F9,"")
B52: Operación | C52: Etiquetado | D52: Etiquetado | E52: Etiquetado | F52: Etiquetado | G52: Etiquetado | H52: Etiquetado
B53: Tiempo (horas)
B54: Tiempo (uds /hora)
B55: Unidad de referencia
B56: Personas
B57: Tiempo (horas) | C57: =+IFERROR(IF(C53>0,C53*C56,C55/C54*C56),"") | D57: =+IFERROR(IF(D53>0,D53*D56,D55/D54*D56),"") | E57: =+IFERROR(IF(E53>0,E53*E56,E55/E54*E56),"") | F57: =+IFERROR(IF(F53>0,F53*F56,F55/F54*F56),"")
B58: €/ud tubo
B59: Total (€/ ud) | C59: =+IFERROR(($C$14*C57)/C9,"") | D59: =+IFERROR(($C$14*D57)/D9,"") | E59: =+IFERROR(($C$14*E57)/E9,"") | F59: =+IFERROR(($C$14*F57)/F9,"")
B62: Total Jumsa (€/ud) | C62: =+SUM(C23,C32,C41,C50,C59) -> 0.1624 | D62: =+SUM(D23,D32,D41,D50,D59) -> 0.146 | E62: =+SUM(E23,E32,E41,E50,E59) -> 0.168 | F62: =+SUM(F23,F32,F41,F50,F59) -> 0.1554 | G62: =+SUM(G23,G32,G41,G50,G59) -> 0.116 | H62: =+SUM(H23,H32,H41,H50,H59) -> 0.104
B65: Materiales (€/ud.)
B67: Componente | C67: Importe (€/ud.) | D67: Importe (€/ud.) | E67: Importe (€/ud.) | F67: Importe (€/ud.) | G67: Importe (€/ud.) | H67: Importe (€/ud.)
B68: Envase | C68: 0 | D68: 0 | E68: 0 | F68: 0 | G68: 0 | H68: 0
B69: Componente | C69: 0 | D69: 0 | E69: 0 | F69: 0 | G69: 0 | H69: 0
B70: Estuche | C70: 0 | D70: 0 | E70: 0 | F70: 0 | G70: 0 | H70: 0
B71: Embalaje | C71: 0.011 | D71: 0.011 | E71: 0.014 | F71: 0.014 | G71: 0.011 | H71: 0.011 | J71: Se reparte el coste del embalaje en función de la cantidad de tubos que caben
B72: Etiqueta | C72: 0 | D72: 0 | E72: 0 | F72: 0 | G72: 0 | H72: 0 | J72: J002 bien posicionados
B73: Palet | C73: 0 | D73: 0 | E73: 0 | F73: 0 | G73: 0 | H73: 0 | J73: El posicionado influye en el coste , porque requiere +1 pax
B74: Subtotal materiales | C74: =+SUM(C68:C73) -> 0.011 | D74: =+SUM(D68:D73) -> 0.011 | E74: =+SUM(E68:E73) -> 0.014 | F74: =+SUM(F68:F73) -> 0.014 | G74: =+SUM(G68:G73) -> 0.011 | H74: =+SUM(H68:H73) -> 0.011 | J74: Se reparte el coste del embalaje en función de la cantidad de tubos que caben
B76: Ajuste | C76: 0 | D76: 0 | E76: 0 | F76: 0 | G76: 0 | H76: 0
B78: Total materiales | C78: =+C74*(1+C76) -> 0.011 | D78: =+D74*(1+D76) -> 0.011 | E78: =+E74*(1+E76) -> 0.014 | F78: =+F74*(1+F76) -> 0.014 | G78: =+G74*(1+G76) -> 0.011 | H78: =+H74*(1+H76) -> 0.011
B81: TOTAL PRESUPUESTO
B83: Total Planta Jumsa (€/ud) | C83: =+C62 -> 0.1624 | D83: =+D62 -> 0.146 | E83: =+E62 -> 0.168 | F83: =+F62 -> 0.1554 | G83: =+G62 -> 0.116 | H83: =+H62 -> 0.104
C84: =+C83*1000 -> 162.4 | D84: =+D83*1000 -> 146 | E84: =+E83*1000 -> 168 | F84: =+F83*1000 -> 155.4 | G84: =+G83*1000 -> 116 | H84: =+H83*1000 -> 104
B86: Total Materiales (€/ud) | C86: =+C78 -> 0.011 | D86: =+D78 -> 0.011 | E86: =+E78 -> 0.014 | F86: =+F78 -> 0.014 | G86: =+G78 -> 0.011 | H86: =+H78 -> 0.011
C87: =+C86*1000 -> 11 | D87: =+D86*1000 -> 11 | E87: =+E86*1000 -> 14 | F87: =+F86*1000 -> 14 | G87: =+G86*1000 -> 11 | H87: =+H86*1000 -> 11
B89: Total | C89: =+C83+C86 -> 0.1734 | D89: =+D83+D86 -> 0.157 | E89: =+E83+E86 -> 0.182 | F89: =+F83+F86 -> 0.1694 | G89: =+G83+G86 -> 0.127 | H89: =+H83+H86 -> 0.115
C90: =+C89*1000 -> 173.4 | D90: =+D89*1000 -> 157 | E90: =+E89*1000 -> 182 | F90: =+F89*1000 -> 169.4 | G90: =+G89*1000 -> 127 | H90: =+H89*1000 -> 115

Sheet Mesobeauty
C2: Presp | E2: 476/25
C3: Datos
C4: Cliente | E4: MESOBEAUTY
C5: Producto | E5: EDT PROMOCIONAL 10ML.
C6: Servicio | E6: Bulk + Envs
C7: Materiales Lab. Coper
C8: Envase
C9: Capacidad envase (ml): | E9: 10 | G9: Es de 10 ml pero pone 11 ml para el calculo de coste coper
C10: Kilos | E10: 3000
C11: Unidades | E11: 300000 | G11: Comentarios
C14: Planta Coper
C17: MP
C19: Coste MP de la fórmula (€/kg) | E19: 5.12 | G19: Compras - escandallo Angel
C22: MO Planta Coper
C24: Elegir tarifa €/hora | E24: TARIFA 1 (FORMULACIONES HASTA 10€ MP)– 223
C25: Tasa €/hora 2026 | E25: 239 | G25: Parece ser tarifa 1 incrementada
C27: Tiempo de fabricación | E27: 675 | G27: Escandallo Angel | I27: Puede incluir tiempo de pesada , fabricación, maceración, enfriamento, análisis, limpieza y ajuste de color
C29: Total MO (€/kg) | E29: =+(E27/60)*(E25/E10) -> 0.89625
C32: Otros conceptos planta Coper
C34: Análisis Bacterias | E34: 0
C35: Análisis Mohos y Levaduras | E35: 0
C36: Nº de Bidones de 100 kg (uds) | E36: 0
C37: Nº de Bidones de 1000 kg | E37: 3
C38: Nº de palets | E38: 2
C39: Nº de transportes | E39: 3 | G39: Cuanto lleva cada transporte?
C41: Analisis bacterias (€/kg) | E41: =+E34*'BD tasas y precios'!C30/E10 -> 0
C42: Analisis Mohos y levaduras (€/kg) | E42: =+E35*'BD tasas y precios'!C29/E10 -> 0
C43: Bidon 100kg (€/kg) | E43: =+'BD tasas y precios'!C28*E36/E10 -> 0
C44: Bidon 1000k (€/kg) | E44: =+'BD tasas y precios'!C27*E37/E10 -> 0.21
C45: Palet euro. (€/kg) | E45: =+'BD tasas y precios'!C26*E38/E10 -> 0 | G45: No se porque no cotiza el palet
C46: Transporte a Jumsa (€/Kg) | E46: =+'BD tasas y precios'!C25*E39/E10 -> 0.017
C48: Total otros conceptos (€/kg) | E48: =+SUM(E41,E42,E43,E44,E45,E46) -> 0.227
C51: Total planta Coper
C53: Coste Mp | E53: =+E19 -> 5.12
C54: Coste Mo | E54: =+E29 -> 0.89625
C55: Coste otros | E55: =+E48 -> 0.227
C56: Subtotal (Mp + MO +Otros) (€/Kg) | E56: =+SUM(E53,E54,E55) -> 6.24325
C58: Porcentaje de merma (%) | E58: 0.03 | G58: Vincular Formules
C60: Merma (€/kg) | E60: =+E56*E58 -> 0.1872975
C62: Porcentaje de residuos (%) | E62: 0.05 | G62: Vincular Formules
C64: Residuos (€/kg) | E64: =+(E56+E60)*E62 -> 0.32152738
C66: Total Planta Coper (€/kg) | E66: =+E56+E60+E64 -> 6.7520749
C68: Total Coper (€/ud) | E68: =+E66/1000*E9 -> 0.067520749
E69: =+E68*1000 -> 67.520749
C72: MO Planta Jumsa
C74: Tasa €/hora | E74: =+'BD tasas y precios'!$C$12*1.02 -> 32.844
C76: Operación | E76: Envasado Tubo
C77: Tiempo (horas) | E77: n.d.
C78: Tiempo (uds /hora) | E78: n.d.
C79: Unidad de referencia | E79: n.a.
C80: Personas | E80: 0
C81: Tiempo (horas) | E81: n.a.
C82: €/ud tubo | E82: 0
C83: Total (€/ ud) | E83: =+IF(E80>0,E82*1.85,E82) -> 0
C85: Operación | E85: Envasado Estándar
C86: Tiempo (horas)
C87: Tiempo (uds /hora) | E87: 1400
C89: Unidad de referencia | E89: =+E11 -> 300000
C91: Personas | E91: 4.5
C93: Tiempo (horas) | E93: =+IFERROR(IF(E86>0,E86*E91,E89/E87*E91),"") -> 964.28571
C95: Total (€/ ud) | E95: =+IFERROR(($E$74*E93)/E11,"") -> 0.10557
C97: Operación | E97: Estuchado
C98: Tiempo (horas)
C99: Tiempo (uds /hora) | E99: 850
C101: Unidad de referencia | E101: =+E11 -> 300000
C103: Personas | E103: 3.5
C105: Tiempo (horas) | E105: =+IFERROR(IF(E98>0,E98*E103,E101/E99*E103),"") -> 1235.2941
C107: Total (€/ ud) | E107: =+IFERROR(($E$74*E105)/E11,"") -> 0.13524
C109: Operación | E109: Env. + Est.
C110: Tiempo (horas)
C111: Tiempo (uds /hora)
C113: Unidad de referencia | E113: =+E11 -> 300000
C115: Personas
C117: Tiempo (horas) | E117: =+IFERROR(IF(E110>0,E110*E115,E113/E111*E115),"")
C119: Total (€/ ud) | E119: =+IFERROR(($E$74*E117)/E11,"")
C121: Operación | E121: Etiquetado
C122: Tiempo (horas)
C123: Tiempo (uds /hora)
C125: Unidad de referencia | E125: =+E11 -> 300000
C127: Personas
C129: Tiempo (horas) | E129: =+IFERROR(IF(E122>0,E122*E127,E125/E123*E127),"")
C131: Total (€/ ud) | E131: =+IFERROR(($E$74*E129)/E11,"")
C134: Total Jumsa (€/ud) | E134: =+SUM(E83,E95,E107,E119,E131) -> 0.24081
E135: =+E134*1000 -> 240.81
C137: Materiales (€/ud.)
C139: Componente | E139: Importe (€/ud.)
C140: Envase | D140: FRASCO 15ML. INCOLORO SERIGRAFIA 1 TINTA | E140: 0.2209 | G140: Ir anotando en bbdd
C141: Componente | D141: VAPO NEGRO ROSCA CON TAPA MONTADA | E141: 0.265
C142: Estuche | D142: ESTUCHE FOLDING BLANCO | E142: 0.053
C143: Embalaje | D143: EMBALAJE 250 U | E143: 0.009
C144: Etiqueta | D144: ETIQUETA DE EMBALAJE | E144: 0.001
C145: Palet | D145: PALETS EURO 8000 U. | E145: 0.002
C147: Subtotal materiales | E147: =+SUM(E140:E145) -> 0.5509
C149: Ajuste | E149: 0.25
C151: Total materiales | E151: =+E147*(1+E149) -> 0.688625
C154: TOTAL PRESUPUESTO
C156: Total Planta Coper (€/ud) | E156: =+E68 -> 0.067520749
E157: =+E156*1000 -> 67.520749
C159: Total Planta Jumsa (€/ud) | E159: =+E134 -> 0.24081
E160: =+E159*1000 -> 240.81
...

Sheet Modelo FS
C2: Presp | E2: 476/25
C3: Datos
C4: Cliente
C5: Producto
C6: Servicio
C7: Materiales Lab. Coper
C8: Envase
C9: Capacidad envase (ml):
C10: Kilos
C11: Unidades | G11: Comentarios
C14: Planta Coper
C17: MP
C19: Coste MP de la fórmula (€/kg) | G19: Hay que seleccionar del escandallo los tiempos en función del escalado
C22: MO Planta Coper
C24: Elegir tarifa €/hora | E24: TARIFA 1 (FORMULACIONES HASTA 10€ MP)– 223
C25: Tasa €/hora 2026 | E25: =+VLOOKUP(E24,'BD tasas y precios'!B3:E7,2,0) -> 223
C27: Tiempo de fabricación
C29: Total MO (€/kg) | E29: =+IFERROR((E27/60)*(E25/E10),"")
C32: Otros conceptos planta Coper
C34: Análisis Bacterias | E34: 0
C35: Análisis Mohos y Levaduras | E35: 0
C36: Nº de Bidones de 100 kg (uds) | E36: 0
C37: Nº de Bidones de 1000 kg | E37: 0
C38: Nº de palets | E38: 0
C39: Nº de transportes | E39: 0
C41: Analisis bacterias (€/kg) | E41: =+IFERROR(E34*'BD tasas y precios'!C30/E10,"")
C42: Analisis Mohos y levaduras (€/kg) | E42: =+IFERROR(E35*'BD tasas y precios'!C29/E10,"")
C43: Bidon 100kg (€/kg) | E43: =+IFERROR('BD tasas y precios'!C28*E36/E10,"")
C44: Bidon 1000k (€/kg) | E44: =+IFERROR('BD tasas y precios'!C27*E37/E10,"")
C45: Palet euro. (€/kg) | E45: =+IFERROR('BD tasas y precios'!C26*E38/E10,"")
C46: Transporte a Jumsa (€/Kg) | E46: =+IFERROR('BD tasas y precios'!C25*E39/E10,"")
C48: Total otros conceptos (€/kg) | E48: =+SUM(E41,E42,E43,E44,E45,E46) -> 0
C51: Total planta Coper
C53: Coste Mp | E53: =+E19 -> 0
C54: Coste Mo | E54: =+E29
C55: Coste otros | E55: =+E48 -> 0
C56: Subtotal (Mp + MO +Otros) (€/Kg) | E56: =+SUM(E53,E54,E55) -> 0
C58: Porcentaje de merma (%) | E58: 0 | G58: Vincular a BD
C60: Merma (€/kg) | E60: =+E56*E58 -> 0
C62: Porcentaje de residuos (%) | E62: 0 | G62: Vincular a BD
C64: Residuos (€/kg) | E64: =+(E56+E60)*E62 -> 0
C66: Total Planta Coper (€/kg) | E66: =+E56+E60+E64 -> 0
C68: Total Coper (€/ud) | E68: =+E66/1000*E9 -> 0
E69: =+E68*1000 -> 0
C72: MO Planta Jumsa
C74: Tasa €/hora | E74: =+'BD tasas y precios'!$C$12*1.02 -> 32.844
C76: Operación | E76: Envasado Tubo
C77: Tiempo (horas) | E77: n.d.
C78: Tiempo (uds /hora) | E78: n.d.
C79: Unidad de referencia | E79: n.a.
C80: Personas | E80: 0
C81: Tiempo (horas) | E81: n.a.
C82: €/ud tubo | E82: 0
C83: Total (€/ ud) | E83: =+IF(E80>0,E82*1.85,E82) -> 0
C85: Operación | E85: Envasado Estándar
C86: Tiempo (horas)
C87: Tiempo (uds /hora)
C89: Unidad de referencia | E89: =+E11 -> 0
C91: Personas
C93: Tiempo (horas) | E93: =+IFERROR(IF(E86>0,E86*E91,E89/E87*E91),"")
C95: Total (€/ ud) | E95: =+IFERROR(($E$74*E93)/E11,"")
C97: Operación | E97: Estuchado
C98: Tiempo (horas)
C99: Tiempo (uds /hora)
C101: Unidad de referencia | E101: =+E11 -> 0
C103: Personas
C105: Tiempo (horas) | E105: =+IFERROR(IF(E98>0,E98*E103,E101/E99*E103),"")
C107: Total (€/ ud) | E107: =+IFERROR(($E$74*E105)/E11,"")
C109: Operación | E109: Env. + Est.
C110: Tiempo (horas)
C111: Tiempo (uds /hora)
C113: Unidad de referencia | E113: =+E11 -> 0
C115: Personas
C117: Tiempo (horas) | E117: =+IFERROR(IF(E110>0,E110*E115,E113/E111*E115),"")
C119: Total (€/ ud) | E119: =+IFERROR(($E$74*E117)/E11,"")
C121: Operación | E121: Etiquetado
C122: Tiempo (horas)
C123: Tiempo (uds /hora)
C125: Unidad de referencia | E125: =+E11 -> 0
C127: Personas
C129: Tiempo (horas) | E129: =+IFERROR(IF(E122>0,E122*E127,E125/E123*E127),"")
C131: Total (€/ ud) | E131: =+IFERROR(($E$74*E129)/E11,"")
C134: Total Jumsa (€/ud) | E134: =+SUM(E83,E95,E107,E119,E131) -> 0
E135: =+E134*1000 -> 0
C137: Materiales (€/ud.)
C139: Componente | E139: Importe (€/ud.)
C140: Envase
C141: Componente
C142: Estuche
C143: Embalaje
C144: Etiqueta
C145: Palet
C147: Subtotal materiales | E147: =+SUM(E140:E145) -> 0
C149: Ajuste | E149: 0.25
C151: Total materiales | E151: =+E147*(1+E149) -> 0
C154: TOTAL PRESUPUESTO
C156: Total Planta Coper (€/ud) | E156: =+E68 -> 0
E157: =+E156*1000 -> 0
C159: Total Planta Jumsa (€/ud) | E159: =+E134 -> 0
E160: =+E159*1000 -> 0
...

Sheet DB >>

Sheet TD tarifas
B3: DB ENVASADO TUBO
B5: Operación | C5: Envasado Tubos
B6: Tipo envase | C6: Estándar
B7: Capcidad (ml) | C7: 15
B8: Cantidad | C8: 20000
B10: € / ud. | C10: € / millar ud.
B11: 0.089 | C11: 89
B14: DB ENVASADO, ESTUCHADO Y ETIQUETADO
B16: Operación | C16: Envasado
B17: Envase | C17: Frascos
B18: Capcidad (ml) | C18: De 30 a 60
B19: Tipo envase | C19: Estándar
B21: Etiquetas de fila | C21: Unidades | D21: Pers. | E21: Tiempo (horas) | F21: Tiempo (uds /hora) | G21: Coste unidad Tarifas
B22: 500 unid. | C22: 500 | D22: 3.5 | E22: 2.5 | G22: 0.5635
B23: 1000 unid. | C23: 1000 | D23: 3.5 | E23: 3 | G23: 0.3381
B24: 1500 a 2500 unid | C24: 1500 | D24: 3.5 | F24: 500 | G24: 0.2254
B25: 2501 a 5000 unid. | C25: 3000 | D25: 3.5 | F25: 600 | G25: 0.18783333
B26: 5001 a 15000 unid. | C26: 15000 | D26: 3.5 | F26: 700 | G26: 0.161
B27: Total general | C27: 21000 | D27: 17.5 | E27: 5.5 | F27: 1800 | G27: 1.4758333

Sheet BD tasas y precios
B3: Tasas Coper (€/hora) | C3: 2024 | D3: 2025 | E3: 2026
B4: TARIFA 1 (FORMULACIONES HASTA 10€ MP)– 223 | C4: 223 | D4: =+C4*1.035 -> 230.805 | E4: =+D4*1.03 -> 237.72915
B5: TARIFA 2 (FORMULACIONES SUPERIORES A 10€ MP – 274 | C5: 274 | D5: =+C5*1.035 -> 283.59 | E5: =+D5*1.03 -> 292.0977
B6: TARIFA 3 (FORMULACIONES DE MAS DE 20€ MP - 325 | C6: 325 | D6: =+C6*1.035 -> 336.375 | E6: =+D6*1.03 -> 346.46625
B7: TARIFA 4 (FORMULACIONES DE MAS DE 30€ MP - 440 | C7: 440 | D7: =+C7*1.035 -> 455.4 | E7: =+D7*1.03 -> 469.062
B11: Tasas Jumsa (€/Hora) | C11: 2024 | D11: 2025 | E11: 2026
C12: 32.2 | D12: 32.2 | E12: 32.2
B15: Tabla precios escandallo Angel - otros conceptos
B16: Garrafa 60L (€) | C16: 20
B17: Cubo 10L (€) | C17: 5
B18: Bidon 60L (€) | C18: 20
B19: Deposito 100L (€) | C19: 140 | D19: 1
B20: Palet (€) | C20: 0
B21: Transporte a Jumsa (€) | C21: 10 | D21: A jumsa
B24: Tabla precios varios
B25: Precio transporte a JUMSA (€) | C25: 17
B26: Precio euro palet (€) | C26: 0
B27: Precio contenedor 1000 kg (€) | C27: 210
B28: Precio Bidon 100 kg (€) | C28: 26
B29: Precio analisis Mohoos Y levaduras (€) | C29: 68
B30: Precio analisis bacterias (€) | C30: 42
B33: Porcentaje Merma | C33: 70
B34: Merma > 70Kgs | C34: 0.08
B35: Merma 70 < 1500 | C35: 0.05
B39: Porcentaje Residuos
B40: Según Kilos
B41: General | C41: 0.025
B42: 150 | C42: 0.03
B43: 500 | C43: 0.03
B44: 1000 | C44: 0.03
B45: 1500 | C45: 0.03
B46: 2500 | C46: 0.03
B47: 3000 | C47: 0.03
B48: 4000 | C48: 0.03
B54: Tabla selección Si/No
B55: Si
B56: No

Sheet BD Jumsa
M1: ='BD tasas y precios'!E12 -> 32.2
A2: Envase | B2: Tipo envase | C2: Capcidad min (ml) | D2: Capcidad max (ml) | E2: Operación | F2: Escalado min (uds) | G2: Escalado max (uds) | H2: Cantidad | I2: Personas | J2: Tiempo (h) | K2: Piezas /hora | L2: Total horas | M2: Coste operación | N2: Coste unidad | O2: Coste Millar | P2: Turnos
A3: Frascos | B3: Estándar | C3: 0 | D3: 25 | E3: Etiquetado cilíndrico plastico | F3: 0 | G3: 500 | H3: 500 | I3: 1.5 | J3: 1 | L3: =+I3*J3 -> 1.5 | M3: =+L3*$M$1 -> 48.3 | N3: =+M3/H3 -> 0.0966 | O3: =+N3*1000 -> 96.6 | P3: =+J3/8 -> 0.125 | R3: Que era el 1400 en vermell??
A4: Frascos | B4: Estándar | C4: 0 | D4: 25 | E4: Etiquetado plano plástico | F4: 0 | G4: 500 | H4: 500 | I4: 1.5 | J4: 1.5 | L4: =+I4*J4 -> 2.25 | M4: =+L4*$M$1 -> 72.45 | N4: =+M4/H4 -> 0.1449 | O4: =+N4*1000 -> 144.9 | P4: =+J4/8 -> 0.1875 | R4: Lo de rollon 1 pax más es en todas??
A5: Frascos | B5: Frascos Agrafados | C5: 0 | D5: 25 | E5: Etiquetado cilíndrico plastico | F5: 0 | G5: 500 | H5: 500 | I5: 1.5 | J5: 1.5 | L5: =+I5*J5 -> 2.25 | M5: =+L5*$M$1 -> 72.45 | N5: =+M5/H5 -> 0.1449 | O5: =+N5*1000 -> 144.9 | P5: =+J5/8 -> 0.1875
A6: Frascos | B6: Frascos Agrafados | C6: 0 | D6: 25 | E6: Etiquetado plano plástico | F6: 0 | G6: 500 | H6: 500 | I6: 1.5 | J6: 1.5 | L6: =+I6*J6 -> 2.25 | M6: =+L6*$M$1 -> 72.45 | N6: =+M6/H6 -> 0.1449 | O6: =+N6*1000 -> 144.9 | P6: =+J6/8 -> 0.1875
A7: Frascos | B7: Frascos Agrafados | C7: 0 | D7: 25 | E7: Etiquetado plano vidrio | F7: 0 | G7: 500 | H7: 500 | I7: 1.5 | J7: 2.5 | L7: =+I7*J7 -> 3.75 | M7: =+L7*$M$1 -> 120.75 | N7: =+M7/H7 -> 0.2415 | O7: =+N7*1000 -> 241.5 | P7: =+J7/8 -> 0.3125
A8: Frascos | B8: Estándar | C8: 0 | D8: 25 | E8: Etiquetado cilíndrico vidrio | F8: 0 | G8: 500 | H8: 500 | I8: 2.5 | J8: 1 | L8: =+I8*J8 -> 2.5 | M8: =+L8*$M$1 -> 80.5 | N8: =+M8/H8 -> 0.161 | O8: =+N8*1000 -> 161 | P8: =+J8/8 -> 0.125
A9: Frascos | B9: Estándar | C9: 0 | D9: 25 | E9: Etiquetado plano vidrio | F9: 0 | G9: 500 | H9: 500 | I9: 2.5 | J9: 1.5 | L9: =+I9*J9 -> 3.75 | M9: =+L9*$M$1 -> 120.75 | N9: =+M9/H9 -> 0.2415 | O9: =+N9*1000 -> 241.5 | P9: =+J9/8 -> 0.1875
A10: Frascos | B10: Frascos Agrafados | C10: 0 | D10: 25 | E10: Etiquetado cilíndrico vidrio | F10: 0 | G10: 500 | H10: 500 | I10: 2.5 | J10: 1.5 | L10: =+I10*J10 -> 3.75 | M10: =+L10*$M$1 -> 120.75 | N10: =+M10/H10 -> 0.2415 | O10: =+N10*1000 -> 241.5 | P10: =+J10/8 -> 0.1875
A11: Frascos | B11: Estándar | C11: 0 | D11: 25 | E11: Envasado | F11: 0 | G11: 500 | H11: 500 | I11: 3.5 | J11: 2.5 | L11: =+I11*J11 -> 8.75 | M11: =+L11*$M$1 -> 281.75 | N11: =+M11/H11 -> 0.5635 | O11: =+N11*1000 -> 563.5 | P11: =+J11/8 -> 0.3125
A12: Frascos | B12: Estándar | C12: 0 | D12: 25 | E12: Envasado + estuchado | F12: 0 | G12: 500 | H12: 500 | I12: 4.5 | J12: 2.5 | L12: =+I12*J12 -> 11.25 | M12: =+L12*$M$1 -> 362.25 | N12: =+M12/H12 -> 0.7245 | O12: =+N12*1000 -> 724.5 | P12: =+J12/8 -> 0.3125
A13: Frascos | B13: Frascos Agrafados | C13: 0 | D13: 25 | E13: Envasado | F13: 0 | G13: 500 | H13: 500 | I13: 4.5 | J13: 2.5 | L13: =+I13*J13 -> 11.25 | M13: =+L13*$M$1 -> 362.25 | N13: =+M13/H13 -> 0.7245 | O13: =+N13*1000 -> 724.5 | P13: =+J13/8 -> 0.3125
A14: Frascos | B14: Estándar | C14: 0 | D14: 25 | E14: Estuchado | F14: 0 | G14: 500 | H14: 500 | I14: 3.5 | J14: 1 | L14: =+I14*J14 -> 3.5 | M14: =+L14*$M$1 -> 112.7 | N14: =+M14/H14 -> 0.2254 | O14: =+N14*1000 -> 225.4 | P14: =+J14/8 -> 0.125
A15: Tarros | B15: Estándar | C15: 151 | D15: 300 | E15: Etiquetado cilíndrico plastico | F15: 0 | G15: 500 | H15: 500 | I15: 1.5 | J15: 1.5 | L15: =+I15*J15 -> 2.25 | M15: =+L15*$M$1 -> 72.45 | N15: =+M15/H15 -> 0.1449 | O15: =+N15*1000 -> 144.9 | P15: =+J15/8 -> 0.1875
A16: Tarros | B16: Estándar | C16: 301 | D16: 500 | E16: Etiquetado cilíndrico plastico | F16: 0 | G16: 500 | H16: 500 | I16: 1.5 | J16: 1.5 | L16: =+I16*J16 -> 2.25 | M16: =+L16*$M$1 -> 72.45 | N16: =+M16/H16 -> 0.1449 | O16: =+N16*1000 -> 144.9 | P16: =+J16/8 -> 0.1875
... A19: Frascos | B19: Frascos Agrafados | C19: 0 | D19: 25 | E19: Envasado + estuchado | F19: 0 | G19: 500 | H19: 500 | I19: 5.5 | J19: 2.5 | L19: =+I19*J19 -> 13.75 | M19: =+L19*$M$1 -> 442.75 | N19: =+M19/H19 -> 0.8855 | O19: =+N19*1000 -> 885.5 | P19: =+J19/8 -> 0.3125
A20: Frascos | B20: Estándar | C20: 0 | D20: 25 | E20: Envasado Rollon | F20: 0 | G20: 500 | H20: 500 | I20: =+I4+1 -> 2.5 | J20: 2.5 | L20: =+I20*J20 -> 6.25 | M20: =+L20*$M$1 -> 201.25 | N20: =+M20/H20 -> 0.4025 | O20: =+N20*1000 -> 402.5 | P20: =+J20/8 -> 0.3125
A21: Frascos | B21: Estándar | C21: 0 | D21: 25 | E21: Envasado | F21: 501 | G21: 1000 | H21: 1000 | I21: 3.5 | J21: 3 | L21: =+I21*J21 -> 10.5 | M21: =+L21*$M$1 -> 338.1 | N21: =+M21/H21 -> 0.3381 | O21: =+N21*1000 -> 338.1 | P21: =+J21/8 -> 0.375
A22: Frascos | B22: Frascos Agrafados | C22: 0 | D22: 25 | E22: Envasado | F22: 501 | G22: 1000 | H22: 1000 | I22: 4.5 | J22: 3 | L22: =+I22*J22 -> 13.5 | M22: =+L22*$M$1 -> 434.7 | N22: =+M22/H22 -> 0.4347 | O22: =+N22*1000 -> 434.7 | P22: =+J22/8 -> 0.375
A23: Frascos | B23: Estándar | C23: 0 | D23: 25 | E23: Envasado Rollon | F23: 501 | G23: 1000 | H23: 1000 | I23: =+I19+1 -> 6.5 | J23: 3 | L23: =+I23*J23 -> 19.5 | M23: =+L23*$M$1 -> 627.9 | N23: =+M23/H23 -> 0.6279 | O23: =+N23*1000 -> 627.9 | P23: =+J23/8 -> 0.375
A24: Frascos | B24: Frascos Agrafados | C24: 0 | D24: 25 | E24: Estuchado con interior | F24: 0 | G24: 500 | H24: 500 | I24: 4.5 | J24: 1.5 | L24: =+I24*J24 -> 6.75 | M24: =+L24*$M$1 -> 217.35 | N24: =+M24/H24 -> 0.4347 | O24: =+N24*1000 -> 434.7 | P24: =+J24/8 -> 0.1875
A25: Frascos | B25: Estándar | C25: 0 | D25: 25 | E25: Envasado | F25: 1001 | G25: 2500 | H25: 2500 | I25: 3.5 | K25: 600 | L25: =I25*(H25/K25) -> 14.583333 | M25: =+L25*$M$1 -> 469.58333 | N25: =+M25/H25 -> 0.18783333 | O25: =+N25*1000 -> 187.83333 | P25: =+J25/8 -> 0
A26: Frascos | B26: Frascos Agrafados | C26: 0 | D26: 25 | E26: Envasado | F26: 1001 | G26: 2500 | H26: 2500 | I26: 4.5 | K26: 425 | L26: =I26*(H26/K26) -> 26.470588 | M26: =+L26*$M$1 -> 852.35294 | N26: =+M26/H26 -> 0.34094118 | O26: =+N26*1000 -> 340.94118 | P26: =+J26/8 -> 0
A27: Frascos | B27: Estándar | C27: 0 | D27: 25 | E27: Envasado Rollon | F27: 1001 | G27: 2500 | H27: 2500 | I27: =+I21+1 -> 4.5 | K27: 600 | L27: =I27*(H27/K27) -> 18.75 | M27: =+L27*$M$1 -> 603.75 | N27: =+M27/H27 -> 0.2415 | O27: =+N27*1000 -> 241.5 | P27: =+J27/8 -> 0
A28: Frascos | B28: Estándar | C28: 0 | D28: 25 | E28: Envasado | F28: 2501 | G28: 5000 | H28: 5000 | I28: 3.5 | K28: 700 | L28: =I28*(H28/K28) -> 25 | M28: =+L28*$M$1 -> 805 | N28: =+M28/H28 -> 0.161 | O28: =+N28*1000 -> 161 | P28: =+J28/8 -> 0
A29: Frascos | B29: Frascos Agrafados | C29: 0 | D29: 25 | E29: Envasado | F29: 2501 | G29: 5000 | H29: 5000 | I29: 4.5 | K29: 450 | L29: =I29*(H29/K29) -> 50 | M29: =+L29*$M$1 -> 1610 | N29: =+M29/H29 -> 0.322 | O29: =+N29*1000 -> 322 | P29: =+J29/8 -> 0
A30: Frascos | B30: Estándar | C30: 0 | D30: 25 | E30: Envasado Rollon | F30: 2501 | G30: 5000 | H30: 5000 | I30: =+I24+1 -> 5.5 | K30: 700 | L30: =I30*(H30/K30) -> 39.285714 | M30: =+L30*$M$1 -> 1265 | N30: =+M30/H30 -> 0.253 | O30: =+N30*1000 -> 253 | P30: =+J30/8 -> 0
A31: Frascos | B31: Frascos Agrafados | C31: 0 | D31: 25 | E31: Envasado | F31: 5001 | G31: 10000 | H31: 10000 | I31: 4.5 | K31: 500 | L31: =I31*(H31/K31) -> 90 | M31: =+L31*$M$1 -> 2898 | N31: =+M31/H31 -> 0.2898 | O31: =+N31*1000 -> 289.8 | P31: =+J31/8 -> 0
A32: Frascos | B32: Estándar | C32: 0 | D32: 25 | E32: Etiquetado cilíndrico plastico | F32: 501 | G32: 1000 | H32: 1000 | I32: 1.5 | J32: 1.5 | L32: =+I32*J32 -> 2.25 | M32: =+L32*$M$1 -> 72.45 | N32: =+M32/H32 -> 0.07245 | O32: =+N32*1000 -> 72.45 | P32: =+J32/8 -> 0.1875
A33: Frascos | B33: Estándar | C33: 0 | D33: 25 | E33: Etiquetado plano plástico | F33: 501 | G33: 1000 | H33: 1000 | I33: 1.5 | J33: 2 | L33: =+I33*J33 -> 3 | M33: =+L33*$M$1 -> 96.6 | N33: =+M33/H33 -> 0.0966 | O33: =+N33*1000 -> 96.6 | P33: =+J33/8 -> 0.25
A34: Frascos | B34: Frascos Agrafados | C34: 0 | D34: 25 | E34: Etiquetado cilíndrico plastico | F34: 501 | G34: 1000 | H34: 1000 | I34: 1.5 | J34: 1.5 | L34: =+I34*J34 -> 2.25 | M34: =+L34*$M$1 -> 72.45 | N34: =+M34/H34 -> 0.07245 | O34: =+N34*1000 -> 72.45 | P34: =+J34/8 -> 0.1875
A35: Frascos | B35: Frascos Agrafados | C35: 0 | D35: 25 | E35: Etiquetado plano plástico | F35: 501 | G35: 1000 | H35: 1000 | I35: 1.5 | J35: 2.5 | L35: =+I35*J35 -> 3.75 | M35: =+L35*$M$1 -> 120.75 | N35: =+M35/H35 -> 0.12075 | O35: =+N35*1000 -> 120.75 | P35: =+J35/8 -> 0.3125
A36: Frascos | B36: Estándar | C36: 0 | D36: 25 | E36: Etiquetado cilíndrico vidrio | F36: 501 | G36: 1000 | H36: 1000 | I36: 2.5 | J36: 1.5 | L36: =+I36*J36 -> 3.75 | M36: =+L36*$M$1 -> 120.75 | N36: =+M36/H36 -> 0.12075 | O36: =+N36*1000 -> 120.75 | P36: =+J36/8 -> 0.1875
A37: Frascos | B37: Estándar | C37: 0 | D37: 25 | E37: Etiquetado plano vidrio | F37: 501 | G37: 1000 | H37: 1000 | I37: 2.5 | J37: 2 | L37: =+I37*J37 -> 5 | M37: =+L37*$M$1 -> 161 | N37: =+M37/H37 -> 0.161 | O37: =+N37*1000 -> 161 | P37: =+J37/8 -> 0.25
A38: Tarros | B38: Estándar | C38: 151 | D38: 300 | E38: Etiquetado cilíndrico vidrio | F38: 0 | G38: 500 | H38: 500 | I38: 2.5 | J38: 1.5 | L38: =+I38*J38 -> 3.75 | M38: =+L38*$M$1 -> 120.75 | N38: =+M38/H38 -> 0.2415 | O38: =+N38*1000 -> 241.5 | P38: =+J38/8 -> 0.1875
A39: Tarros | B39: Estándar | C39: 301 | D39: 500 | E39: Etiquetado cilíndrico vidrio | F39: 0 | G39: 500 | H39: 500 | I39: 2.5 | J39: 1.5 | L39: =+I39*J39 -> 3.75 | M39: =+L39*$M$1 -> 120.75 | N39: =+M39/H39 -> 0.2415 | O39: =+N39*1000 -> 241.5 | P39: =+J39/8 -> 0.1875
A40: Tarros | B40: Estándar | C40: 501 | D40: 1000 | E40: Etiquetado cilíndrico vidrio | F40: 0 | G40: 500 | H40: 500 | I40: 2.5 | J40: 1.5 | L40: =+I40*J40 -> 3.75 | M40: =+L40*$M$1 -> 120.75 | N40: =+M40/H40 -> 0.2415 | O40: =+N40*1000 -> 241.5 | P40: =+J40/8 -> 0.1875
A41: Frascos | B41: Frascos Agrafados | C41: 0 | D41: 25 | E41: Etiquetado cilíndrico vidrio | F41: 501 | G41: 1000 | H41: 1000 | I41: 2.5 | J41: 1.5 | L41: =+I41*J41 -> 3.75 | M41: =+L41*$M$1 -> 120.75 | N41: =+M41/H41 -> 0.12075 | O41: =+N41*1000 -> 120.75 | P41: =+J41/8 -> 0.1875
A42: Frascos | B42: Frascos Agrafados | C42: 0 | D42: 25 | E42: Etiquetado plano vidrio | F42: 501 | G42: 1000 | H42: 1000 | I42: 2.5 | J42: 2.5 | L42: =+I42*J42 -> 6.25 | M42: =+L42*$M$1 -> 201.25 | N42: =+M42/H42 -> 0.20125 | O42: =+N42*1000 -> 201.25 | P42: =+J42/8 -> 0.3125
A43: Frascos | B43: Estándar | C43: 0 | D43: 25 | E43: Envasado | F43: 5001 | G43: 15000 | H43: 15000 | I43: 3.5 | K43: 800 | L43: =I43*(H43/K43) -> 65.625 | M43: =+L43*$M$1 -> 2113.125 | N43: =+M43/H43 -> 0.140875 | O43: =+N43*1000 -> 140.875 | P43: =+J43/8 -> 0
A44: Frascos | B44: Estándar | C44: 0 | D44: 25 | E44: Envasado + estuchado | F44: 501 | G44: 1000 | H44: 1000 | I44: 4.5 | J44: 3 | L44: =+I44*J44 -> 13.5 | M44: =+L44*$M$1 -> 434.7 | N44: =+M44/H44 -> 0.4347 | O44: =+N44*1000 -> 434.7 | P44: =+J44/8 -> 0.375
A45: Frascos | B45: Estándar | C45: 0 | D45: 25 | E45: Envasado | F45: 15001 | G45: 999999 | H45: 15000 | I45: 4.5 | K45: 1200 | L45: =I45*(H45/K45) -> 56.25 | M45: =+L45*$M$1 -> 1811.25 | N45: =+M45/H45 -> 0.12075 | O45: =+N45*1000 -> 120.75 | P45: =+J45/8 -> 0
A46: Frascos | B46: Estándar | C46: 0 | D46: 25 | E46: Estuchado | F46: 501 | G46: 1000 | H46: 1000 | I46: 3.5 | J46: 1.5 | L46: =+I46*J46 -> 5.25 | M46: =+L46*$M$1 -> 169.05 | N46: =+M46/H46 -> 0.16905 | O46: =+N46*1000 -> 169.05 | P46: =+J46/8 -> 0.1875
A47: Frascos | B47: Frascos Agrafados | C47: 0 | D47: 25 | E47: Estuchado sin interior | F47: 501 | G47: 1000 | H47: 1000 | I47: 3.5 | J47: 2 | L47: =+I47*J47 -> 7 | M47: =+L47*$M$1 -> 225.4 | N47: =+M47/H47 -> 0.2254 | O47: =+N47*1000 -> 225.4 | P47: =+J47/8 -> 0.25
A48: Frascos | B48: Frascos Agrafados | C48: 0 | D48: 25 | E48: Envasado + estuchado | F48: 501 | G48: 1000 | H48: 1000 | I48: 5.5 | J48: 3 | L48: =+I48*J48 -> 16.5 | M48: =+L48*$M$1 -> 531.3 | N48: =+M48/H48 -> 0.5313 | O48: =+N48*1000 -> 531.3 | P48: =+J48/8 -> 0.375
A49: Frascos | B49: Estándar | C49: 0 | D49: 25 | E49: Envasado Rollon | F49: 5001 | G49: 15000 | H49: 15000 | I49: =+I43+1 -> 4.5 | K49: 800 | L49: =I49*(H49/K49) -> 84.375 | M49: =+L49*$M$1 -> 2716.875 | N49: =+M49/H49 -> 0.181125 | O49: =+N49*1000 -> 181.125 | P49: =+J49/8 -> 0
A50: Frascos | B50: Estándar | C50: 0 | D50: 25 | E50: Envasado Rollon | F50: 15001 | G50: 999999 | H50: 15000 | I50: =+I44+1 -> 5.5 | K50: 1200 | L50: =I50*(H50/K50) -> 68.75 | M50: =+L50*$M$1 -> 2213.75 | N50: =+M50/H50 -> 0.14758333 | O50: =+N50*1000 -> 147.58333 | P50: =+J50/8 -> 0
A51: Frascos | B51: Frascos Agrafados | C51: 0 | D51: 25 | E51: Envasado | F51: 10001 | G51: 999999 | H51: 25000 | I51: 5.5 | K51: 1200 | L51: =I51*(H51/K51) -> 114.58333 | M51: =+L51*$M$1 -> 3689.5833 | N51: =+M51/H51 -> 0.14758333 | O51: =+N51*1000 -> 147.58333 | P51: =+J51/8 -> 0
A52: Frascos | B52: Frascos Agrafados | C52: 0 | D52: 25 | E52: Estuchado con interior | F52: 501 | G52: 1000 | H52: 1000 | I52: 4.5 | J52: 2 | L52: =+I52*J52 -> 9 | M52: =+L52*$M$1 -> 289.8 | N52: =+M52/H52 -> 0.2898 | O52: =+N52*1000 -> 289.8 | P52: =+J52/8 -> 0.25
A53: Frascos | B53: Estándar | C53: 0 | D53: 25 | E53: Etiquetado cilíndrico plastico | F53: 1001 | G53: 2500 | H53: 2500 | I53: 1.5 | K53: 800 | L53: =I53*(H53/K53) -> 4.6875 | M53: =+L53*$M$1 -> 150.9375 | N53: =+M53/H53 -> 0.060375 | O53: =+N53*1000 -> 60.375 | P53: =+J53/8 -> 0
A54: Tarros | B54: Estándar | C54: 151 | D54: 300 | E54: Estuchado | F54: 0 | G54: 500 | H54: 500 | I54: 3.5 | J54: 1.5 | L54: =+I54*J54 -> 5.25 | M54: =+L54*$M$1 -> 169.05 | N54: =+M54/H54 -> 0.3381 | O54: =+N54*1000 -> 338.1 | P54: =+J54/8 -> 0.1875
A55: Tarros | B55: Estándar | C55: 301 | D55: 500 | E55: Estuchado | F55: 0 | G55: 500 | H55: 500 | I55: 3.5 | J55: 1.5 | L55: =+I55*J55 -> 5.25 | M55: =+L55*$M$1 -> 169.05 | N55: =+M55/H55 -> 0.3381 | O55: =+N55*1000 -> 338.1 | P55: =+J55/8 -> 0.1875
A56: Tarros | B56: Estándar | C56: 501 | D56: 1000 | E56: Estuchado | F56: 0 | G56: 500 | H56: 500 | I56: 3.5 | J56: 1.5 | L56: =+I56*J56 -> 5.25 | M56: =+L56*$M$1 -> 169.05 | N56: =+M56/H56 -> 0.3381 | O56: =+N56*1000 -> 338.1 | P56: =+J56/8 -> 0.1875
A57: Frascos | B57: Estándar | C57: 0 | D57: 25 | E57: Etiquetado plano plástico | F57: 1001 | G57: 2500 | H57: 2500 | I57: 1.5 | K57: 600 | L57: =I57*(H57/K57) -> 6.25 | M57: =+L57*$M$1 -> 201.25 | N57: =+M57/H57 -> 0.0805 | O57: =+N57*1000 -> 80.5 | P57: =+J57/8 -> 0
A58: Frascos | B58: Frascos Agrafados | C58: 0 | D58: 25 | E58: Etiquetado cilíndrico plastico | F58: 1001 | G58: 2500 | H58: 2500 | I58: 1.5 | K58: 800 | L58: =I58*(H58/K58) -> 4.6875 | M58: =+L58*$M$1 -> 150.9375 | N58: =+M58/H58 -> 0.060375 | O58: =+N58*1000 -> 60.375 | P58: =+J58/8 -> 0
A59: Frascos | B59: Frascos Agrafados | C59: 0 | D59: 25 | E59: Etiquetado plano plástico | F59: 1001 | G59: 2500 | H59: 2500 | I59: 1.5 | K59: 600 | L59: =I59*(H59/K59) -> 6.25 | M59: =+L59*$M$1 -> 201.25 | N59: =+M59/H59 -> 0.0805 | O59: =+N59*1000 -> 80.5 | P59: =+J59/8 -> 0
A60: Frascos | B60: Estándar | C60: 0 | D60: 25 | E60: Etiquetado cilíndrico vidrio | F60: 1001 | G60: 2500 | H60: 2500 | I60: 2.5 | K60: 800 | L60: =I60*(H60/K60) -> 7.8125 | M60: =+L60*$M$1 -> 251.5625 | N60: =+M60/H60 -> 0.100625 | O60: =+N60*1000 -> 100.625 | P60: =+J60/8 -> 0
A61: Frascos | B61: Estándar | C61: 0 | D61: 25 | E61: Etiquetado plano vidrio | F61: 1001 | G61: 2500 | H61: 2500 | I61: 2.5 | K61: 600 | L61: =I61*(H61/K61) -> 10.416667 | M61: =+L61*$M$1 -> 335.41667 | N61: =+M61/H61 -> 0.13416667 | O61: =+N61*1000 -> 134.16667 | P61: =+J61/8 -> 0
A62: Frascos | B62: Frascos Agrafados | C62: 0 | D62: 25 | E62: Etiquetado cilíndrico vidrio | F62: 1001 | G62: 2500 | H62: 2500 | I62: 2.5 | K62: 800 | L62: =I62*(H62/K62) -> 7.8125 | M62: =+L62*$M$1 -> 251.5625 | N62: =+M62/H62 -> 0.100625 | O62: =+N62*1000 -> 100.625 | P62: =+J62/8 -> 0
A63: Frascos | B63: Frascos Agrafados | C63: 0 | D63: 25 | E63: Etiquetado plano vidrio | F63: 1001 | G63: 2500 | H63: 2500 | I63: 2.5 | K63: 600 | L63: =I63*(H63/K63) -> 10.416667 | M63: =+L63*$M$1 -> 335.41667 | N63: =+M63/H63 -> 0.13416667 | O63: =+N63*1000 -> 134.16667 | P63: =+J63/8 -> 0
A64: Frascos | B64: Estándar | C64: 0 | D64: 25 | E64: Envasado + estuchado | F64: 1001 | G64: 2500 | H64: 2500 | I64: 4.5 | K64: 600 | L64: =I64*(H64/K64) -> 18.75 | M64: =+L64*$M$1 -> 603.75 | N64: =+M64/H64 -> 0.2415 | O64: =+N64*1000 -> 241.5 | P64: =+J64/8 -> 0
A65: Frascos | B65: Estándar | C65: 0 | D65: 25 | E65: Estuchado | F65: 1001 | G65: 2500 | H65: 2500 | I65: 3.5 | K65: 700 | L65: =I65*(H65/K65) -> 12.5 | M65: =+L65*$M$1 -> 402.5 | N65: =+M65/H65 -> 0.161 | O65: =+N65*1000 -> 161 | P65: =+J65/8 -> 0
A66: Frascos | B66: Frascos Agrafados | C66: 0 | D66: 25 | E66: Estuchado sin interior | F66: 1001 | G66: 2500 | H66: 2500 | I66: 3.5 | K66: 550 | L66: =I66*(H66/K66) -> 15.909091 | M66: =+L66*$M$1 -> 512.27273 | N66: =+M66/H66 -> 0.20490909 | O66: =+N66*1000 -> 204.90909 | P66: =+J66/8 -> 0
A67: Frascos | B67: Frascos Agrafados | C67: 0 | D67: 25 | E67: Envasado + estuchado | F67: 1001 | G67: 2500 | H67: 2500 | I67: 5.5 | K67: 425 | L67: =I67*(H67/K67) -> 32.352941 | M67: =+L67*$M$1 -> 1041.7647 | N67: =+M67/H67 -> 0.41670588 | O67: =+N67*1000 -> 416.70588 | P67: =+J67/8 -> 0
A68: Frascos | B68: Frascos Agrafados | C68: 0 | D68: 25 | E68: Estuchado con interior | F68: 1001 | G68: 2500 | H68: 2500 | I68: 4.5 | K68: 550 | L68: =I68*(H68/K68) -> 20.454545 | M68: =+L68*$M$1 -> 658.63636 | N68: =+M68/H68 -> 0.26345455 | O68: =+N68*1000 -> 263.45455 | P68: =+J68/8 -> 0
... A75: Frascos | B75: Frascos Agrafados | C75: 0 | D75: 25 | E75: Etiquetado cilíndrico vidrio | F75: 2501 | G75: 5000 | H75: 5000 | I75: 2.5 | K75: 900 | L75: =I75*(H75/K75) -> 13.888889 | M75: =+L75*$M$1 -> 447.22222 | N75: =+M75/H75 -> 0.089444444 | O75: =+N75*1000 -> 89.444444 | P75: =+J75/8 -> 0
A76: Tarros | B76: Estándar | C76: 151 | D76: 300 | E76: Envasado + estuchado | F76: 0 | G76: 500 | H76: 500 | I76: 4.5 | J76: 2.5 | L76: =+I76*J76 -> 11.25 | M76: =+L76*$M$1 -> 362.25 | N76: =+M76/H76 -> 0.7245 | O76: =+N76*1000 -> 724.5 | P76: =+J76/8 -> 0.3125
A77: Frascos | B77: Frascos Agrafados | C77: 0 | D77: 25 | E77: Etiquetado plano vidrio | F77: 2501 | G77: 5000 | H77: 5000 | I77: 2.5 | K77: 700 | L77: =I77*(H77/K77) -> 17.857143 | M77: =+L77*$M$1 -> 575 | N77: =+M77/H77 -> 0.115 | O77: =+N77*1000 -> 115 | P77: =+J77/8 -> 0
A78: Frascos | B78: Estándar | C78: 0 | D78: 25 | E78: Envasado + estuchado | F78: 2501 | G78: 5000 | H78: 5000 | I78: 4.5 | K78: 700 | L78: =I78*(H78/K78) -> 32.142857 | M78: =+L78*$M$1 -> 1035 | N78: =+M78/H78 -> 0.207 | O78: =+N78*1000 -> 207 | P78: =+J78/8 -> 0
A79: Frascos | B79: Frascos Agrafados | C79: 0 | D79: 25 | E79: Envasado + estuchado | F79: 2501 | G79: 5000 | H79: 5000 | I79: 5.5 | K79: 450 | L79: =I79*(H79/K79) -> 61.111111 | M79: =+L79*$M$1 -> 1967.7778 | N79: =+M79/H79 -> 0.39355556 | O79: =+N79*1000 -> 393.55556 | P79: =+J79/8 -> 0
A80: Tarros | B80: Estándar | C80: 301 | D80: 500 | E80: Envasado + estuchado | F80: 0 | G80: 500 | H80: 500 | I80: 4.5 | J80: 2.5 | L80: =+I80*J80 -> 11.25 | M80: =+L80*$M$1 -> 362.25 | N80: =+M80/H80 -> 0.7245 | O80: =+N80*1000 -> 724.5 | P80: =+J80/8 -> 0.3125
A81: Frascos | B81: Estándar | C81: 0 | D81: 25 | E81: Estuchado | F81: 2501 | G81: 5000 | H81: 5000 | I81: 3.5 | K81: 750 | L81: =I81*(H81/K81) -> 23.333333 | M81: =+L81*$M$1 -> 751.33333 | N81: =+M81/H81 -> 0.15026667 | O81: =+N81*1000 -> 150.26667 | P81: =+J81/8 -> 0
A82: Frascos | B82: Frascos Agrafados | C82: 0 | D82: 25 | E82: Estuchado sin interior | F82: 2501 | G82: 5000 | H82: 5000 | I82: 3.5 | K82: 575 | L82: =I82*(H82/K82) -> 30.434783 | M82: =+L82*$M$1 -> 980 | N82: =+M82/H82 -> 0.196 | O82: =+N82*1000 -> 196 | P82: =+J82/8 -> 0
A83: Frascos | B83: Frascos Agrafados | C83: 0 | D83: 25 | E83: Estuchado con interior | F83: 2501 | G83: 5000 | H83: 5000 | I83: 4.5 | K83: 575 | L83: =I83*(H83/K83) -> 39.130435 | M83: =+L83*$M$1 -> 1260 | N83: =+M83/H83 -> 0.252 | O83: =+N83*1000 -> 252 | P83: =+J83/8 -> 0
A84: Tarros | B84: Estándar | C84: 501 | D84: 1000 | E84: Envasado + estuchado | F84: 0 | G84: 500 | H84: 500 | I84: 4.5 | J84: 2.5 | L84: =+I84*J84 -> 11.25 | M84: =+L84*$M$1 -> 362.25 | N84: =+M84/H84 -> 0.7245 | O84: =+N84*1000 -> 724.5 | P84: =+J84/8 -> 0.3125
A85: Frascos | B85: Frascos Agrafados | C85: 0 | D85: 25 | E85: Estuchado sin interior | F85: 5001 | G85: 10000 | H85: 10000 | I85: 3.5 | K85: 600 | L85: =I85*(H85/K85) -> 58.333333 | M85: =+L85*$M$1 -> 1878.3333 | N85: =+M85/H85 -> 0.18783333 | O85: =+N85*1000 -> 187.83333 | P85: =+J85/8 -> 0
A86: Frascos | B86: Frascos Agrafados | C86: 0 | D86: 25 | E86: Estuchado con interior | F86: 5001 | G86: 10000 | H86: 10000 | I86: 4.5 | K86: 600 | L86: =I86*(H86/K86) -> 75 | M86: =+L86*$M$1 -> 2415 | N86: =+M86/H86 -> 0.2415 | O86: =+N86*1000 -> 241.5 | P86: =+J86/8 -> 0
A87: Frascos | B87: Estándar | C87: 0 | D87: 25 | E87: Envasado + estuchado | F87: 5001 | G87: 15000 | H87: 15000 | I87: 4.5 | K87: 800 | L87: =I87*(H87/K87) -> 84.375 | M87: =+L87*$M$1 -> 2716.875 | N87: =+M87/H87 -> 0.181125 | O87: =+N87*1000 -> 181.125 | P87: =+J87/8 -> 0
A88: Frascos | B88: Estándar | C88: 0 | D88: 25 | E88: Estuchado | F88: 5001 | G88: 15000 | H88: 15000 | I88: 3.5 | K88: 850 | L88: =I88*(H88/K88) -> 61.764706 | M88: =+L88*$M$1 -> 1988.8235 | N88: =+M88/H88 -> 0.13258824 | O88: =+N88*1000 -> 132.58824 | P88: =+J88/8 -> 0
A89: Frascos | B89: Estándar | C89: 0 | D89: 25 | E89: Etiquetado cilíndrico plastico | F89: 5001 | G89: 25000 | H89: 25000 | I89: 1.5 | K89: 1100 | L89: =I89*(H89/K89) -> 34.090909 | M89: =+L89*$M$1 -> 1097.7273 | N89: =+M89/H89 -> 0.043909091 | O89: =+N89*1000 -> 43.909091 | P89: =+J89/8 -> 0
A90: Frascos | B90: Estándar | C90: 0 | D90: 25 | E90: Etiquetado plano plástico | F90: 5001 | G90: 25000 | H90: 25000 | I90: 1.5 | K90: 1000 | L90: =I90*(H90/K90) -> 37.5 | M90: =+L90*$M$1 -> 1207.5 | N90: =+M90/H90 -> 0.0483 | O90: =+N90*1000 -> 48.3 | P90: =+J90/8 -> 0
A91: Frascos | B91: Frascos Agrafados | C91: 0 | D91: 25 | E91: Etiquetado cilíndrico plastico | F91: 5001 | G91: 25000 | H91: 25000 | I91: 1.5 | K91: 1100 | L91: =I91*(H91/K91) -> 34.090909 | M91: =+L91*$M$1 -> 1097.7273 | N91: =+M91/H91 -> 0.043909091 | O91: =+N91*1000 -> 43.909091 | P91: =+J91/8 -> 0
A92: Frascos | B92: Frascos Agrafados | C92: 0 | D92: 25 | E92: Etiquetado plano plástico | F92: 5001 | G92: 25000 | H92: 25000 | I92: 1.5 | K92: 1000 | L92: =I92*(H92/K92) -> 37.5 | M92: =+L92*$M$1 -> 1207.5 | N92: =+M92/H92 -> 0.0483 | O92: =+N92*1000 -> 48.3 | P92: =+J92/8 -> 0
A93: Frascos | B93: Estándar | C93: 0 | D93: 25 | E93: Etiquetado cilíndrico vidrio | F93: 5001 | G93: 25000 | H93: 25000 | I93: 2.5 | K93: 1100 | L93: =I93*(H93/K93) -> 56.818182 | M93: =+L93*$M$1 -> 1829.5455 | N93: =+M93/H93 -> 0.073181818 | O93: =+N93*1000 -> 73.181818 | P93: =+J93/8 -> 0
A94: Frascos | B94: Estándar | C94: 0 | D94: 25 | E94: Etiquetado plano vidrio | F94: 5001 | G94: 25000 | H94: 25000 | I94: 2.5 | K94: 1000 | L94: =I94*(H94/K94) -> 62.5 | M94: =+L94*$M$1 -> 2012.5 | N94: =+M94/H94 -> 0.0805 | O94: =+N94*1000 -> 80.5 | P94: =+J94/8 -> 0
A95: Frascos | B95: Frascos Agrafados | C95: 0 | D95: 25 | E95: Etiquetado cilíndrico vidrio | F95: 5001 | G95: 25000 | H95: 25000 | I95: 2.5 | K95: 1100 | L95: =I95*(H95/K95) -> 56.818182 | M95: =+L95*$M$1 -> 1829.5455 | N95: =+M95/H95 -> 0.073181818 | O95: =+N95*1000 -> 73.181818 | P95: =+J95/8 -> 0
A96: Frascos | B96: Frascos Agrafados | C96: 0 | D96: 25 | E96: Etiquetado plano vidrio | F96: 5001 | G96: 25000 | H96: 25000 | I96: 2.5 | K96: 1000 | L96: =I96*(H96/K96) -> 62.5 | M96: =+L96*$M$1 -> 2012.5 | N96: =+M96/H96 -> 0.0805 | O96: =+N96*1000 -> 80.5 | P96: =+J96/8 -> 0
A97: Tarros | B97: Estándar | C97: 151 | D97: 300 | E97: Etiquetado cilíndrico plastico | F97: 501 | G97: 1000 | H97: 1000 | I97: 1.5 | J97: 2 | L97: =+I97*J97 -> 3 | M97: =+L97*$M$1 -> 96.6 | N97: =+M97/H97 -> 0.0966 | O97: =+N97*1000 -> 96.6 | P97: =+J97/8 -> 0.25
A98: Tarros | B98: Estándar | C98: 301 | D98: 500 | E98: Etiquetado cilíndrico plastico | F98: 501 | G98: 1000 | H98: 1000 | I98: 1.5 | J98: 2 | L98: =+I98*J98 -> 3 | M98: =+L98*$M$1 -> 96.6 | N98: =+M98/H98 -> 0.0966 | O98: =+N98*1000 -> 96.6 | P98: =+J98/8 -> 0.25
A99: Tarros | B99: Estándar | C99: 501 | D99: 1000 | E99: Etiquetado cilíndrico plastico | F99: 501 | G99: 1000 | H99: 1000 | I99: 1.5 | J99: 2 | L99: =+I99*J99 -> 3 | M99: =+L99*$M$1 -> 96.6 | N99: =+M99/H99 -> 0.0966 | O99: =+N99*1000 -> 96.6 | P99: =+J99/8 -> 0.25
A100: Frascos | B100: Frascos Agrafados | C100: 0 | D100: 25 | E100: Envasado + estuchado | F100: 5001 | G100: 25000 | H100: 25000 | I100: 5.5 | K100: 500 | L100: =I100*(H100/K100) -> 275 | M100: =+L100*$M$1 -> 8855 | N100: =+M100/H100 -> 0.3542 | O100: =+N100*1000 -> 354.2 | P100: =+J100/8 -> 0
A101: Frascos | B101: Frascos Agrafados | C101: 0 | D101: 25 | E101: Estuchado sin interior | F101: 10001 | G101: 999999 | H101: 25000 | I101: 3.5 | K101: 625 | L101: =I101*(H101/K101) -> 140 | M101: =+L101*$M$1 -> 4508 | N101: =+M101/H101 -> 0.18032 | O101: =+N101*1000 -> 180.32 | P101: =+J101/8 -> 0
A102: Frascos | B102: Frascos Agrafados | C102: 0 | D102: 25 | E102: Estuchado con interior | F102: 10001 | G102: 999999 | H102: 25000 | I102: 4.5 | K102: 625 | L102: =I102*(H102/K102) -> 180 | M102: =+L102*$M$1 -> 5796 | N102: =+M102/H102 -> 0.23184 | O102: =+N102*1000 -> 231.84 | P102: =+J102/8 -> 0
A103: Frascos | B103: Estándar | C103: 26 | D103: 60 | E103: Etiquetado cilíndrico plastico | F103: 0 | G103: 500 | H103: 500 | I103: 1.5 | J103: 1 | L103: =+I103*J103 -> 1.5 | M103: =+L103*$M$1 -> 48.3 | N103: =+M103/H103 -> 0.0966 | O103: =+N103*1000 -> 96.6 | P103: =+J103/8 -> 0.125
A104: Frascos | B104: Estándar | C104: 26 | D104: 60 | E104: Etiquetado plano plástico | F104: 0 | G104: 500 | H104: 500 | I104: 1.5 | J104: 1.5 | L104: =+I104*J104 -> 2.25 | M104: =+L104*$M$1 -> 72.45 | N104: =+M104/H104 -> 0.1449 | O104: =+N104*1000 -> 144.9 | P104: =+J104/8 -> 0.1875
A105: Frascos | B105: Frascos Agrafados | C105: 26 | D105: 60 | E105: Etiquetado cilíndrico plastico | F105: 0 | G105: 500 | H105: 500 | I105: 1.5 | J105: 1.5 | L105: =+I105*J105 -> 2.25 | M105: =+L105*$M$1 -> 72.45 | N105: =+M105/H105 -> 0.1449 | O105: =+N105*1000 -> 144.9 | P105: =+J105/8 -> 0.1875
A106: Frascos | B106: Frascos Agrafados | C106: 26 | D106: 60 | E106: Etiquetado plano plástico | F106: 0 | G106: 500 | H106: 500 | I106: 1.5 | J106: 1.5 | L106: =+I106*J106 -> 2.25 | M106: =+L106*$M$1 -> 72.45 | N106: =+M106/H106 -> 0.1449 | O106: =+N106*1000 -> 144.9 | P106: =+J106/8 -> 0.1875
A107: Frascos | B107: Frascos Agrafados | C107: 26 | D107: 60 | E107: Etiquetado plano vidrio | F107: 0 | G107: 500 | H107: 500 | I107: 1.5 | J107: 2.5 | L107: =+I107*J107 -> 3.75 | M107: =+L107*$M$1 -> 120.75 | N107: =+M107/H107 -> 0.2415 | O107: =+N107*1000 -> 241.5 | P107: =+J107/8 -> 0.3125
A108: Frascos | B108: Estándar | C108: 26 | D108: 60 | E108: Etiquetado cilíndrico vidrio | F108: 0 | G108: 500 | H108: 500 | I108: 2.5 | J108: 1 | L108: =+I108*J108 -> 2.5 | M108: =+L108*$M$1 -> 80.5 | N108: =+M108/H108 -> 0.161 | O108: =+N108*1000 -> 161 | P108: =+J108/8 -> 0.125
...

Sheet BD Tubos
R1: ='BD tasas y precios'!E12 -> 32.2
B2: Envase | C2: Tipo envase | D2: Capacidad min (ml) | E2: Capacidad max (ml) | F2: Operación | G2: Escalado min (uds) | H2: Escalado max (uds) | I2: Cantidad | J2: Personas | K2: Tiempo (h) | L2: Piezas /hora | M2: Total horas | N2: Coste operación | O2: Coste unidad | P2: Coste Millar | Q2: Turnos
B3: Tubos | C3: Elípticos (+85%) | D3: 0 | E3: 15 | F3: Envasado Tubos | G3: 0 | H3: 1000 | I3: 1000 | O3: =+P3/1000 -> 0.218 | P3: 218
B4: Tubos | C4: Elípticos (+85%) | D4: 0 | E4: 15 | F4: Envasado Tubos | G4: 1001 | H4: 2000 | I4: 2000 | O4: =+P4/1000 -> 0.375 | P4: 375
B5: Tubos | C5: Elípticos (+85%) | D5: 0 | E5: 15 | F5: Envasado Tubos | G5: 2001 | H5: 2500 | I5: 2500 | O5: =+P5/1000 -> 0.21 | P5: 210
B6: Tubos | C6: Elípticos (+85%) | D6: 0 | E6: 15 | F6: Envasado Tubos | G6: 3001 | H6: 5000 | I6: 5000 | O6: =+P6/1000 -> 0.156 | P6: 156
B7: Tubos | C7: Elípticos (+85%) | D7: 0 | E7: 15 | F7: Envasado Tubos | G7: 5001 | H7: 10000 | I7: 10000 | O7: =+P7/1000 -> 0.146 | P7: 146
B8: Tubos | C8: Elípticos (+85%) | D8: 0 | E8: 15 | F8: Envasado Tubos | G8: 10001 | H8: 20000 | I8: 20000 | O8: =+P8/1000 -> 0.127 | P8: 127
B9: Tubos | C9: Elípticos (+85%) | D9: 0 | E9: 15 | F9: Envasado Tubos | G9: 20001 | H9: 50000 | I9: 50000 | O9: =+P9/1000 -> 0.112 | P9: 112
B10: Tubos | C10: Elípticos (+85%) | D10: 0 | E10: 15 | F10: Envasado Tubos | G10: 50001 | H10: 999999 | I10: 100000 | O10: =+P10/1000 -> 0.375 | P10: 375
B11: Tubos | C11: Estándar | D11: 0 | E11: 15 | F11: Envasado Tubos | G11: 0 | H11: 1000 | I11: 1000 | O11: =+P11/1000 -> 0.207 | P11: 207
B12: Tubos | C12: Estándar | D12: 0 | E12: 15 | F12: Envasado Tubos | G12: 1001 | H12: 2000 | I12: 2000 | O12: =+P12/1000 -> 0.153 | P12: 153
B13: Tubos | C13: Estándar | D13: 0 | E13: 15 | F13: Envasado Tubos | G13: 2001 | H13: 2500 | I13: 2500 | O13: =+P13/1000 -> 0.132 | P13: 132
B14: Tubos | C14: Estándar | D14: 0 | E14: 15 | F14: Envasado Tubos | G14: 3001 | H14: 5000 | I14: 5000 | O14: =+P14/1000 -> 0.117 | P14: 117
... B63: Tubos | C63: Ovalado (+40%) | D63: 16 | E63: 30 | F63: Envasado Tubos | G63: 5001 | H63: 10000 | I63: 10000 | O63: =+P63/1000 -> 0.076 | P63: 76
B64: Tubos | C64: Ovalado (+40%) | D64: 16 | E64: 30 | F64: Envasado Tubos | G64: 10001 | H64: 20000 | I64: 20000 | O64: =+P64/1000 -> 0.4033 | P64: =+P3*1.85 -> 403.3
B65: Tubos | C65: Ovalado (+40%) | D65: 16 | E65: 30 | F65: Envasado Tubos | G65: 20001 | H65: 50000 | I65: 50000 | O65: =+P65/1000 -> 0.69375 | P65: =+P4*1.85 -> 693.75
B66: Tubos | C66: Ovalado (+40%) | D66: 16 | E66: 30 | F66: Envasado Tubos | G66: 50001 | H66: 999999 | I66: 100000 | O66: =+P66/1000 -> 0.3885 | P66: =+P5*1.85 -> 388.5
B67: Tubos | C67: Elípticos (+85%) | D67: 31 | E67: 50 | F67: Envasado Tubos | G67: 0 | H67: 1000 | I67: 1000 | O67: =+P67/1000 -> 0.2886 | P67: =+P6*1.85 -> 288.6
B68: Tubos | C68: Elípticos (+85%) | D68: 31 | E68: 50 | F68: Envasado Tubos | G68: 1001 | H68: 2000 | I68: 2000 | O68: =+P68/1000 -> 0.2701 | P68: =+P7*1.85 -> 270.1
B69: Tubos | C69: Elípticos (+85%) | D69: 31 | E69: 50 | F69: Envasado Tubos | G69: 2001 | H69: 2500 | I69: 2500 | O69: =+P69/1000 -> 0.23495 | P69: =+P8*1.85 -> 234.95
B70: Tubos | C70: Elípticos (+85%) | D70: 31 | E70: 50 | F70: Envasado Tubos | G70: 3001 | H70: 5000 | I70: 5000 | O70: =+P70/1000 -> 0.2072 | P70: =+P9*1.85 -> 207.2
B71: Tubos | C71: Elípticos (+85%) | D71: 31 | E71: 50 | F71: Envasado Tubos | G71: 5001 | H71: 10000 | I71: 10000 | O71: =+P71/1000 -> 0.69375 | P71: =+P10*1.85 -> 693.75
B72: Tubos | C72: Elípticos (+85%) | D72: 31 | E72: 50 | F72: Envasado Tubos | G72: 10001 | H72: 20000 | I72: 20000 | O72: =+P72/1000 -> 0.38295 | P72: =+P11*1.85 -> 382.95
B73: Tubos | C73: Elípticos (+85%) | D73: 31 | E73: 50 | F73: Envasado Tubos | G73: 20001 | H73: 50000 | I73: 50000 | O73: =+P73/1000 -> 0.28305 | P73: =+P12*1.85 -> 283.05
B74: Tubos | C74: Elípticos (+85%) | D74: 31 | E74: 50 | F74: Envasado Tubos | G74: 50001 | H74: 999999 | I74: 100000 | O74: =+P74/1000 -> 0.2442 | P74: =+P13*1.85 -> 244.2
B75: Tubos | C75: Estándar | D75: 31 | E75: 50 | F75: Envasado Tubos | G75: 0 | H75: 1000 | I75: 1000 | O75: =+P75/1000 -> 0.21645 | P75: =+P14*1.85 -> 216.45
... B124: Tubos | C124: Ovalado (+40%) | D124: 51 | E124: 75 | F124: Envasado Tubos | G124: 1001 | H124: 2000 | I124: 2000 | O124: =+P124/1000 -> 0.1406 | P124: =+P63*1.85 -> 140.6
B125: Tubos | C125: Ovalado (+40%) | D125: 51 | E125: 75 | F125: Envasado Tubos | G125: 2001 | H125: 2500 | I125: 2500 | O125: =+P125/1000 -> 0.4033 | P125: =+P3*1.85 -> 403.3
B126: Tubos | C126: Ovalado (+40%) | D126: 51 | E126: 75 | F126: Envasado Tubos | G126: 3001 | H126: 5000 | I126: 5000 | O126: =+P126/1000 -> 0.69375 | P126: =+P4*1.85 -> 693.75
B127: Tubos | C127: Ovalado (+40%) | D127: 51 | E127: 75 | F127: Envasado Tubos | G127: 5001 | H127: 10000 | I127: 10000 | O127: =+P127/1000 -> 0.3885 | P127: =+P5*1.85 -> 388.5
B128: Tubos | C128: Ovalado (+40%) | D128: 51 | E128: 75 | F128: Envasado Tubos | G128: 10001 | H128: 20000 | I128: 20000 | O128: =+P128/1000 -> 0.2886 | P128: =+P6*1.85 -> 288.6
B129: Tubos | C129: Ovalado (+40%) | D129: 51 | E129: 75 | F129: Envasado Tubos | G129: 20001 | H129: 50000 | I129: 50000 | O129: =+P129/1000 -> 0.2701 | P129: =+P7*1.85 -> 270.1
B130: Tubos | C130: Ovalado (+40%) | D130: 51 | E130: 75 | F130: Envasado Tubos | G130: 50001 | H130: 999999 | I130: 100000 | O130: =+P130/1000 -> 0.23495 | P130: =+P8*1.85 -> 234.95
B131: Tubos | C131: Elípticos (+85%) | D131: 76 | E131: 100 | F131: Envasado Tubos | G131: 0 | H131: 1000 | I131: 1000 | O131: =+P131/1000 -> 0.2072 | P131: =+P9*1.85 -> 207.2
B132: Tubos | C132: Elípticos (+85%) | D132: 76 | E132: 100 | F132: Envasado Tubos | G132: 1001 | H132: 2000 | I132: 2000 | O132: =+P132/1000 -> 0.69375 | P132: =+P10*1.85 -> 693.75
B133: Tubos | C133: Elípticos (+85%) | D133: 76 | E133: 100 | F133: Envasado Tubos | G133: 2001 | H133: 2500 | I133: 2500 | O133: =+P133/1000 -> 0.38295 | P133: =+P11*1.85 -> 382.95
B134: Tubos | C134: Elípticos (+85%) | D134: 76 | E134: 100 | F134: Envasado Tubos | G134: 3001 | H134: 5000 | I134: 5000 | O134: =+P134/1000 -> 0.28305 | P134: =+P12*1.85 -> 283.05
B135: Tubos | C135: Elípticos (+85%) | D135: 76 | E135: 100 | F135: Envasado Tubos | G135: 5001 | H135: 10000 | I135: 10000 | O135: =+P135/1000 -> 0.2442 | P135: =+P13*1.85 -> 244.2
B136: Tubos | C136: Elípticos (+85%) | D136: 76 | E136: 100 | F136: Envasado Tubos | G136: 10001 | H136: 20000 | I136: 20000 | O136: =+P136/1000 -> 0.21645 | P136: =+P14*1.85 -> 216.45
... B185: Tubos | C185: Ovalado (+40%) | D185: 101 | E185: 125 | F185: Envasado Tubos | G185: 5001 | H185: 10000 | I185: 10000 | O185: =+P185/1000 -> 0.1406 | P185: =+P63*1.85 -> 140.6
B186: Tubos | C186: Ovalado (+40%) | D186: 101 | E186: 125 | F186: Envasado Tubos | G186: 10001 | H186: 20000 | I186: 20000 | O186: =+P186/1000 -> 0.3052 | P186: =+P3*1.4 -> 305.2 | Q186: =+Q3*1.4 -> 0
B187: Tubos | C187: Elípticos (+85%) | D187: 126 | E187: 150 | F187: Envasado Tubos | G187: 0 | H187: 1000 | I187: 1000 | O187: =+P187/1000 -> 0.525 | P187: =+P4*1.4 -> 525
B188: Tubos | C188: Elípticos (+85%) | D188: 126 | E188: 150 | F188: Envasado Tubos | G188: 1001 | H188: 2000 | I188: 2000 | O188: =+P188/1000 -> 0.294 | P188: =+P5*1.4 -> 294
B189: Tubos | C189: Elípticos (+85%) | D189: 126 | E189: 150 | F189: Envasado Tubos | G189: 2001 | H189: 2500 | I189: 2500 | O189: =+P189/1000 -> 0.2184 | P189: =+P6*1.4 -> 218.4
B190: Tubos | C190: Elípticos (+85%) | D190: 126 | E190: 150 | F190: Envasado Tubos | G190: 3001 | H190: 5000 | I190: 5000 | O190: =+P190/1000 -> 0.2044 | P190: =+P7*1.4 -> 204.4
B191: Tubos | C191: Elípticos (+85%) | D191: 126 | E191: 150 | F191: Envasado Tubos | G191: 5001 | H191: 10000 | I191: 10000 | O191: =+P191/1000 -> 0.1778 | P191: =+P8*1.4 -> 177.8
B192: Tubos | C192: Elípticos (+85%) | D192: 126 | E192: 150 | F192: Envasado Tubos | G192: 10001 | H192: 20000 | I192: 20000 | O192: =+P192/1000 -> 0.1568 | P192: =+P9*1.4 -> 156.8
B193: Tubos | C193: Elípticos (+85%) | D193: 126 | E193: 150 | F193: Envasado Tubos | G193: 20001 | H193: 50000 | I193: 50000 | O193: =+P193/1000 -> 0.525 | P193: =+P10*1.4 -> 525
B194: Tubos | C194: Elípticos (+85%) | D194: 126 | E194: 150 | F194: Envasado Tubos | G194: 50001 | H194: 999999 | I194: 100000 | O194: =+P194/1000 -> 0.2898 | P194: =+P11*1.4 -> 289.8
B195: Tubos | C195: Estándar | D195: 126 | E195: 150 | F195: Envasado Tubos | G195: 0 | H195: 1000 | I195: 1000 | O195: =+P195/1000 -> 0.2142 | P195: =+P12*1.4 -> 214.2
B196: Tubos | C196: Estándar | D196: 126 | E196: 150 | F196: Envasado Tubos | G196: 1001 | H196: 2000 | I196: 2000 | O196: =+P196/1000 -> 0.1848 | P196: =+P13*1.4 -> 184.8
B197: Tubos | C197: Estándar | D197: 126 | E197: 150 | F197: Envasado Tubos | G197: 2001 | H197: 2500 | I197: 2500 | O197: =+P197/1000 -> 0.1638 | P197: =+P14*1.4 -> 163.8
B198: Tubos | C198: Estándar | D198: 126 | E198: 150 | F198: Envasado Tubos | G198: 3001 | H198: 5000 | I198: 5000 | O198: =+P198/1000 -> 0.1498 | P198: =+P15*1.4 -> 149.8
... B246: Tubos | C246: Ovalado (+40%) | D246: 201 | E246: 250 | F246: Envasado Tubos | G246: 2501 | H246: 3000 | I246: 3000 | O246: =+P246/1000 -> 0.1064 | P246: =+P63*1.4 -> 106.4

Sheet tarifas Word JUMSA 
A1: 2025 | E1: FRASCOS COSMETICA | L1: COSTE FIJO: (ENVASADO - 281 €) (ETIQUETADO - 96 €)
A2: FRASCOS COSMETICA CAPACIDAD 1ML A 25ML
C4: Etiquetado cilíndrico plastico | F4: Etiquetado cilíndrico vidrio | I4: Etiquetado plano plástico | L4: Etiquetado plano vidrio
Q5: Com juguen el salts
A6: 500 unid. | C6: 1hx1,5p | D6: =(1*1.5)*(32.2)/(500)*(1000) -> 96.6 | F6: 1hx2,5p | G6: =(1*2.5)*(32.2)/(500)*(1000) -> 161 | I6: 1,5hx1,5p | J6: =(1.5*1.5)*(32.2)/(500)*(1000) -> 144.9 | L6: 1,5hx2,5p | M6: =(1.5*2.5)*(32.2)/(500)*(1000) -> 241.5
A7: 1000 unid. | C7: 1,5hx1,5p | D7: =(1.5*1.5)*(32.2)/(1000)*(1000) -> 72.45 | F7: 1,5hx2,5p | G7: =(1.5*2.5)*(32.2)/(1000)*(1000) -> 120.75 | I7: 2hx1,5p | J7: =(2*1.5)*(32.2)/(1000)*(1000) -> 96.6 | L7: 2hx2,5p | M7: =(2*2.5)*(32.2)/(1000)*(1000) -> 161
A8: 1500 a 2500 unid | C8: 800h/1,5p | D8: =(1*1.5)*(32.2)/(800)*(1000) -> 60.375 | F8: 800h/2,5p | G8: =(1*2.5)*(32.2)/(800)*(1000) -> 100.625 | I8: 600h/1,5p | J8: =(1*1.5)*(32.2)/(600)*(1000) -> 80.5 | L8: 600h/2,5p | M8: =(1*2.5)*(32.2)/(600)*(1000) -> 134.16667
A9: 2501 a 5000 unid. | C9: 900h/1,5p | D9: =(1*1.5)*(32.2)/(900)*(1000) -> 53.666667 | F9: 900h/2,5p | G9: =(1*2.5)*(32.2)/(900)*(1000) -> 89.444444 | H9: ok | I9: 700h/1,5p | J9: =(1*1.5)*(32.2)/(700)*(1000) -> 69 | L9: 700h/2,5p | M9: =(1*2.5)*(32.2)/(700)*(1000) -> 115
A10: 5001 a 25000 unid. | C10: 1100h/1,5p | D10: =(1*1.5)*(32.2)/(1100)*(1000) -> 43.909091 | E10: 2000 | F10: 1100h/2,5p | G10: =(1*2.5)*(32.2)/(1100)*(1000) -> 73.181818 | I10: 1000h/1,5p | J10: =(1*1.5)*(32.2)/(1000)*(1000) -> 48.3 | L10: 1000h/2,5p | M10: =(1*2.5)*(32.2)/(1000)*(1000) -> 80.5
C13: Envasado | F13: Envasado + estuchado | I13: Estuchado
A15: 500 unid. | C15: 2,5h x 3,5p | D15: =(2.5*3.5)*(32.2)/(500)*(1000) -> 563.5 | F15: 2,5h x 4,5p | G15: =(2.5*4.5)*(32.2)/(500)*(1000) -> 724.5 | I15: 1h x 3,5p | J15: =(1*3.5)*(32.2)/(500)*(1000) -> 225.4
A16: 1000 unid. | C16: 3h x 3,5p | D16: =(3*3.5)*(32.2)/(1000)*(1000) -> 338.1 | F16: 3h x 4,5p | G16: =(3*4.5)*(32.2)/(1000)*(1000) -> 434.7 | I16: 1,5h x 3,5p | J16: =(1.5*3.5)*(32.2)/(1000)*(1000) -> 169.05
A17: 1500 a 2500 unid | C17: 600h/3,5p | D17: =(1*3.5)*(32.2)/(600)*(1000) -> 187.83333 | E17: OK | F17: 600h/4,5p | G17: =(1*4.5)*(32.2)/(600)*(1000) -> 241.5 | H17: 500 | I17: 700h/3,5p | J17: =(1*3.5)*(32.2)/(700)*(1000) -> 161
A18: 2501 a 5000 unid. | C18: 700h/3,5p | D18: =(1*3.5)*(32.2)/(700)*(1000) -> 161 | E18: ok | F18: 700h/4,5p | G18: =(1*4.5)*(32.2)/(700)*(1000) -> 207 | I18: 750h/3,5p | J18: =(1*3.5)*(32.2)/(750)*(1000) -> 150.26667 | Q18: Que son els vermells
A19: 5001 a 15000 unid. | C19: 800h/3,5p | D19: =(1*3.5)*(32.2)/(800)*(1000) -> 140.875 | F19: 800h/4,5p | G19: =(1*4.5)*(32.2)/(800)*(1000) -> 181.125 | H19: 750 | I19: 850h/3,5p | J19: =(1*3.5)*(32.2)/(850)*(1000) -> 132.58824 | K19: 800 | Q19: Que era el 1400 en vermell??
A20: 15000+ | B20: 1400 | C20: 1200h/4,5p | D20: =(1*4.5)*(32.2)/(1200)*(1000) -> 120.75 | Q20: Lo de rollon 1 pax más es en todas??
C21: rollon 1 persona más
A23: FRASCOS COSMETICA CAPACIDAD 30ML A 60ML
C25: Etiquetado cilíndrico plastico | F25: Etiquetado cilíndrico vidrio | I25: Etiquetado plano plástico | L25: Etiquetado plano vidrio
A27: 500 unid. | C27: 1hx1,5p | D27: =(1*1.5)*(32.2)/(500)*(1000) -> 96.6 | F27: 1hx2,5p | G27: =(1*2.5)*(32.2)/(500)*(1000) -> 161 | I27: 1,5hx1,5p | J27: =(1.5*1.5)*(32.2)/(500)*(1000) -> 144.9 | L27: 1,5hx2,5p | M27: =(1.5*2.5)*(32.2)/(500)*(1000) -> 241.5
A28: 1000 unid. | C28: 1,5hx1,5p | D28: =(1.5*1.5)*(32.2)/(1000)*(1000) -> 72.45 | F28: 1,5hx2,5p | G28: =(1.5*2.5)*(32.2)/(1000)*(1000) -> 120.75 | I28: 2hx1,5p | J28: =(2*1.5)*(32.2)/(1000)*(1000) -> 96.6 | L28: 2hx2,5p | M28: =(2*2.5)*(32.2)/(1000)*(1000) -> 161
A29: 1500 a 2500 unid | C29: 800h/1,5p | D29: =(1*1.5)*(32.2)/(800)*(1000) -> 60.375 | F29: 800h/2,5p | G29: =(1*2.5)*(32.2)/(800)*(1000) -> 100.625 | I29: 600h/1,5p | J29: =(1*1.5)*(32.2)/(600)*(1000) -> 80.5 | L29: 600h/2,5p | M29: =(1*2.5)*(32.2)/(600)*(1000) -> 134.16667
A30: 2501 a 5000 unid. | C30: 900h/1,5p | D30: =(1*1.5)*(32.2)/(900)*(1000) -> 53.666667 | F30: 900h/2,5p | G30: =(1*2.5)*(32.2)/(900)*(1000) -> 89.444444 | H30: 850 | I30: 700h/1,5p | J30: =(1*1.5)*(32.2)/(700)*(1000) -> 69 | L30: 700h/2,5p | M30: =(1*2.5)*(32.2)/(700)*(1000) -> 115
A31: 5001 a 25000 unid. | C31: 1100h/1,5p | D31: =(1*1.5)*(32.2)/(1100)*(1000) -> 43.909091 | F31: 1100h/2,5p | G31: =(1*2.5)*(32.2)/(1100)*(1000) -> 73.181818 | I31: 1000h/1,5p | J31: =(1*1.5)*(32.2)/(1000)*(1000) -> 48.3 | L31: 1000h/2,5p | M31: =(1*2.5)*(32.2)/(1000)*(1000) -> 80.5
C34: Envasado | F34: Envasado + estuchado | I34: Estuchado
A36: 500 unid. | C36: 2,5h x 3,5p | D36: =(2.5*3.5)*(32.2)/(500)*(1000) -> 563.5 | F36: 2,5h x 4,5p | G36: =(2.5*4.5)*(32.2)/(500)*(1000) -> 724.5 | I36: 1h x 3,5p | J36: =(1*3.5)*(32.2)/(500)*(1000) -> 225.4
A37: 1000 unid. | C37: 3h x 3,5p | D37: =(3*3.5)*(32.2)/(1000)*(1000) -> 338.1 | F37: 3h x 4,5p | G37: =(3*4.5)*(32.2)/(1000)*(1000) -> 434.7 | I37: 1,5h x 3,5p | J37: =(1.5*3.5)*(32.2)/(1000)*(1000) -> 169.05
A38: 1500 a 2500 unid | C38: 500h/3,5p | D38: =(1*3.5)*(32.2)/(500)*(1000) -> 225.4 | E38: 525h | F38: 500h/4,5p | G38: =(1*4.5)*(32.2)/(500)*(1000) -> 289.8 | H38: 525h | I38: 675h/3,5p | J38: =(1*3.5)*(32.2)/(675)*(1000) -> 166.96296
A39: 2501 a 5000 unid. | C39: 600h/3,5p | D39: =(1*3.5)*(32.2)/(600)*(1000) -> 187.83333 | E39: 625hi | F39: 600h/4,5p | G39: =(1*4.5)*(32.2)/(600)*(1000) -> 241.5 | H39: 625h | I39: 725h/3,5p | J39: =(1*3.5)*(32.2)/(725)*(1000) -> 155.44828 | K39: OK
A40: 5001 a 25000 unid. | C40: 700h/3,5p | D40: =(1*3.5)*(32.2)/(700)*(1000) -> 161 | E40: ok | F40: 700h/4,5p | G40: =(1*4.5)*(32.2)/(700)*(1000) -> 207 | H40: ok | I40: 825h/3,5p | J40: =(1*3.5)*(32.2)/(825)*(1000) -> 136.60606 | K40: 800
A41: AUTOMATICO | D41: 116 | Q41: que es automático???
A44: FRASCOS COSMETICA CAPACIDAD 75ML A 150ML
C46: Etiquetado cilíndrico plastico | F46: Etiquetado cilíndrico vidrio | I46: Etiquetado plano plástico | L46: Etiquetado plano vidrio
A48: 500 unid. | C48: 1,5hx1,5p | D48: =(1.5*1.5)*(32.2)/(500)*(1000) -> 144.9 | F48: 1,5hx2,5p | G48: =(1.5*2.5)*(32.2)/(500)*(1000) -> 241.5 | I48: 1,5hx1,5p | J48: =(1.5*1.5)*(32.2)/(500)*(1000) -> 144.9 | L48: 1,5hx2,5p | M48: =(1.5*2.5)*(32.2)/(500)*(1000) -> 241.5
A49: 1000 unid. | C49: 2hx1,5p | D49: =(2*1.5)*(32.2)/(1000)*(1000) -> 96.6 | F49: 2hx2,5p | G49: =(2*2.5)*(32.2)/(1000)*(1000) -> 161 | I49: 2,5hx1,5p | J49: =(2.5*1.5)*(32.2)/(1000)*(1000) -> 120.75 | L49: 2,5hx2,5p | M49: =(2.5*2.5)*(32.2)/(1000)*(1000) -> 201.25
A50: 1500 a 2500 unid | C50: 700h/1,5p | D50: =(1*1.5)*(32.2)/(700)*(1000) -> 69 | F50: 700h/2,5p | G50: =(1*2.5)*(32.2)/(700)*(1000) -> 115 | I50: 600h/1,5p | J50: =(1*1.5)*(32.2)/(600)*(1000) -> 80.5 | L50: 600h/2,5p | M50: =(1*2.5)*(32.2)/(600)*(1000) -> 134.16667
A51: 2501 a 5000 unid. | C51: 800h/1,5p | D51: =(1*1.5)*(32.2)/(800)*(1000) -> 60.375 | F51: 800h/2,5p | G51: =(1*2.5)*(32.2)/(800)*(1000) -> 100.625 | I51: 700h/1,5p | J51: =(1*1.5)*(32.2)/(700)*(1000) -> 69 | L51: 700h/2,5p | M51: =(1*2.5)*(32.2)/(700)*(1000) -> 115
A52: 5001 a 25000 unid. | C52: 1100h/1,5p | D52: =(1*1.5)*(32.2)/(1100)*(1000) -> 43.909091 | E52: ok | F52: 1100h/2,5p | G52: =(1*2.5)*(32.2)/(1100)*(1000) -> 73.181818 | I52: 1000h/1,5p | J52: =(1*1.5)*(32.2)/(1000)*(1000) -> 48.3 | L52: 1000h/2,5p | M52: =(1*2.5)*(32.2)/(1000)*(1000) -> 80.5
A53: *En el etiquetado cilindrico de vidrio en el escalado de 500 unidades se ha cambiado el tiempo de 1x2,5p a 1,5x2,5p para que el importe no sea igual que el escalado de 1000 unid
C55: Envasado | F55: Envasado + estuchado | I55: Estuchado | K55: c/interior (Mousse julia)
A57: 500 unid. | C57: 2,5h x 3,5p | D57: =(2.5*3.5)*(32.2)/(500)*(1000) -> 563.5 | F57: 2,5h x 4,5p | G57: =(2.5*4.5)*(32.2)/(500)*(1000) -> 724.5 | I57: 1h x 3,5p | J57: =(1*3.5)*(32.2)/(500)*(1000) -> 225.4
A58: 1000 unid. | C58: 3h x 3,5p | D58: =(3*3.5)*(32.2)/(1000)*(1000) -> 338.1 | E58: ok | F58: 3h x 4,5p | G58: =(3*4.5)*(32.2)/(1000)*(1000) -> 434.7 | I58: 1,5h x 3,5p | J58: =(1.5*3.5)*(32.2)/(1000)*(1000) -> 169.05
A59: 1500 a 2500 unid | C59: 450h/3,5p | D59: =(1*3.5)*(32.2)/(450)*(1000) -> 250.44444 | E59: OK | F59: 450h/4,5p | G59: =(1*4.5)*(32.2)/(450)*(1000) -> 322 | I59: 675h/3,5p | J59: =(1*3.5)*(32.2)/(675)*(1000) -> 166.96296
A60: 2501 a 5000 unid. | C60: 550h/3,5p | D60: =(1*3.5)*(32.2)/(550)*(1000) -> 204.90909 | F60: 550h/4,5p | G60: =(1*4.5)*(32.2)/(550)*(1000) -> 263.45455 | I60: 725h/3,5p | J60: =(1*3.5)*(32.2)/(725)*(1000) -> 155.44828 | K60: 400h/4p
A61: 5001 a 25000 unid. | C61: 650h/3,5p | D61: =(1*3.5)*(32.2)/(650)*(1000) -> 173.38462 | E61: 600 | F61: 650h/4,5p | G61: =(1*4.5)*(32.2)/(650)*(1000) -> 222.92308 | I61: 775h/3,5p | J61: =(1*3.5)*(32.2)/(775)*(1000) -> 145.41935 | K61: 700h/4,5p
A65: FRASCOS COSMETICA CAPACIDAD 200ML A 300ML
C67: Etiquetado cilíndrico plastico | F67: Etiquetado cilíndrico vidrio | I67: Etiquetado plano plástico | L67: Etiquetado plano vidrio
A69: 500 unid. | C69: 1,5hx1,5p | D69: =(1.5*1.5)*(32.2)/(500)*(1000) -> 144.9 | F69: 1,5hx2,5p | G69: =(1.5*2.5)*(32.2)/(500)*(1000) -> 241.5 | I69: 1,5hx1,5p | J69: =(1.5*1.5)*(32.2)/(500)*(1000) -> 144.9 | L69: 1,5hx2,5p | M69: =(1.5*2.5)*(32.2)/(500)*(1000) -> 241.5
A70: 1000 unid. | C70: 2hx1,5p | D70: =(2*1.5)*(32.2)/(1000)*(1000) -> 96.6 | F70: 2hx2,5p | G70: =(2*2.5)*(32.2)/(1000)*(1000) -> 161 | I70: 2,5hx1,5p | J70: =(2.5*1.5)*(32.2)/(1000)*(1000) -> 120.75 | L70: 2,5hx2,5p | M70: =(2.5*2.5)*(32.2)/(1000)*(1000) -> 201.25
A71: 1500 a 2500 unid | C71: 650h/1,5p | D71: =(1*1.5)*(32.2)/(650)*(1000) -> 74.307692 | F71: 650h/2,5p | G71: =(1*2.5)*(32.2)/(650)*(1000) -> 123.84615 | I71: 550h/1,5p | J71: =(1*1.5)*(32.2)/(550)*(1000) -> 87.818182 | L71: 550h/2,5p | M71: =(1*2.5)*(32.2)/(550)*(1000) -> 146.36364
A72: 2501 a 5000 unid. | C72: 750h/1,5p | D72: =(1*1.5)*(32.2)/(750)*(1000) -> 64.4 | E72: 1500 | F72: 750h/2,5p | G72: =(1*2.5)*(32.2)/(750)*(1000) -> 107.33333 | I72: 650h/1,5p | J72: =(1*1.5)*(32.2)/(650)*(1000) -> 74.307692 | L72: 650h/2,5p | M72: =(1*2.5)*(32.2)/(650)*(1000) -> 123.84615
A73: 5001 a 25000 unid. | C73: 1000h/1,5p | D73: =(1*1.5)*(32.2)/(1000)*(1000) -> 48.3 | F73: 1000h/2,5p | G73: =(1*2.5)*(32.2)/(1000)*(1000) -> 80.5 | I73: 900h/1,5p | J73: =(1*1.5)*(32.2)/(900)*(1000) -> 53.666667 | L73: 750h/2,5p | M73: =(1*2.5)*(32.2)/(750)*(1000) -> 107.33333
C76: Envasado | F76: Envasado + estuchado | I76: Estuchado | L76: con interior 1persona +
A78: 500 unid. | C78: 2,5h x 3,5p | D78: =(2.5*3.5)*(32.2)/(500)*(1000) -> 563.5 | F78: 2,5h x 4,5p | G78: =(2.5*4.5)*(32.2)/(500)*(1000) -> 724.5 | I78: 1,5h x 3,5p | J78: =(1.5*3.5)*(32.2)/(500)*(1000) -> 338.1
A79: 1000 unid. | C79: 3h x 3,5p | D79: =(3*3.5)*(32.2)/(1000)*(1000) -> 338.1 | F79: 3h x 4,5p | G79: =(3*4.5)*(32.2)/(1000)*(1000) -> 434.7 | I79: 2h x 3,5p | J79: =(2*3.5)*(32.2)/(1000)*(1000) -> 225.4
A80: 1500 a 2500 unid | C80: 425h/3,5p | D80: =(1*3.5)*(32.2)/(425)*(1000) -> 265.17647 | F80: 425h/4,5p | G80: =(1*4.5)*(32.2)/(425)*(1000) -> 340.94118 | I80: 550h/3,5p | J80: =(1*3.5)*(32.2)/(550)*(1000) -> 204.90909
A81: 2501 a 5000 unid. | C81: 525h/3,5p | D81: =(1*3.5)*(32.2)/(525)*(1000) -> 214.66667 | F81: 525h/4,5p | G81: =(1*4.5)*(32.2)/(525)*(1000) -> 276 | I81: 600h/3,5p | J81: =(1*3.5)*(32.2)/(600)*(1000) -> 187.83333 | K81: ok
A82: 5001 a 25000 unid. | C82: 625h/3,5p | D82: =(1*3.5)*(32.2)/(625)*(1000) -> 180.32 | F82: 625h/4,5p | G82: =(1*4.5)*(32.2)/(625)*(1000) -> 231.84 | I82: 650h/3,5p | J82: =(1*3.5)*(32.2)/(650)*(1000) -> 173.38462 | K82: ok
A86: FRASCOS COSMETICA CAPACIDAD 400ML A 500ML
C88: Etiquetado cilíndrico plastico | F88: Etiquetado cilíndrico vidrio | I88: Etiquetado plano plástico | L88: Etiquetado plano vidrio
A90: 500 unid. | C90: 2hx1,5p | D90: =(2*1.5)*(32.2)/(500)*(1000) -> 193.2 | F90: 2hx2,5p | G90: =(2*2.5)*(32.2)/(500)*(1000) -> 322 | I90: 2hx1,5p | J90: =(2*1.5)*(32.2)/(500)*(1000) -> 193.2 | L90: 2hx2,5p | M90: =(2*2.5)*(32.2)/(500)*(1000) -> 322
A91: 1000 unid. | C91: 2,5hx1,5p | D91: =(2.5*1.5)*(32.2)/(1000)*(1000) -> 120.75 | F91: 2,5hx2,5p | G91: =(2.5*2.5)*(32.2)/(1000)*(1000) -> 201.25 | I91: 3hx1,5p | J91: =(3*1.5)*(32.2)/(1000)*(1000) -> 144.9 | L91: 3hx2,5p | M91: =(3*2.5)*(32.2)/(1000)*(1000) -> 241.5
A92: 1500 a 2500 unid | C92: 600h/1,5p | D92: =(1*1.5)*(32.2)/(600)*(1000) -> 80.5 | F92: 600h/2,5p | G92: =(1*2.5)*(32.2)/(600)*(1000) -> 134.16667 | I92: 500h/1,5p | J92: =(1*1.5)*(32.2)/(500)*(1000) -> 96.6 | L92: 500h/2,5p | M92: =(1*2.5)*(32.2)/(500)*(1000) -> 161
A93: 2501 a 5000 unid. | C93: 700h/1,5p | D93: =(1*1.5)*(32.2)/(700)*(1000) -> 69 | F93: 700h/2,5p | G93: =(1*2.5)*(32.2)/(700)*(1000) -> 115 | I93: 600h/1,5p | J93: =(1*1.5)*(32.2)/(600)*(1000) -> 80.5 | L93: 600h/2,5p | M93: =(1*2.5)*(32.2)/(600)*(1000) -> 134.16667
A94: 5001 a 25000 unid. | C94: 900h/1,5p | D94: =(1*1.5)*(32.2)/(900)*(1000) -> 53.666667 | F94: 900h/2,5p | G94: =(1*2.5)*(32.2)/(900)*(1000) -> 89.444444 | I94: 800h/1,5p | J94: =(1*1.5)*(32.2)/(800)*(1000) -> 60.375 | L94: 800h/2,5p | M94: =(1*2.5)*(32.2)/(800)*(1000) -> 100.625
C97: Envasado | F97: Envasado + estuchado | I97: Estuchado
A99: 500 unid. | C99: 2,5h x 3,5p | D99: =(2.5*3.5)*(32.2)/(500)*(1000) -> 563.5 | F99: 2,5h x 4,5p | G99: =(2.5*4.5)*(32.2)/(500)*(1000) -> 724.5 | I99: 1,5h x 3,5p | J99: =(1.5*3.5)*(32.2)/(500)*(1000) -> 338.1
A100: 1000 unid. | C100: 3h x 3,5p | D100: =(3*3.5)*(32.2)/(1000)*(1000) -> 338.1 | F100: 3h x 4,5p | G100: =(3*4.5)*(32.2)/(1000)*(1000) -> 434.7 | I100: 2,5h x 3,5p | J100: =(2.5*3.5)*(32.2)/(1000)*(1000) -> 281.75
A101: 1500 a 2500 unid | C101: 400h/3,5p | D101: =(1*3.5)*(32.2)/(400)*(1000) -> 281.75 | F101: 400h/4,5p | G101: =(1*4.5)*(32.2)/(400)*(1000) -> 362.25 | I101: 550h/3,5p | J101: =(1*3.5)*(32.2)/(550)*(1000) -> 204.90909
A102: 2501 a 5000 unid. | C102: 425h/3,5p | D102: =(1*3.5)*(32.2)/(425)*(1000) -> 265.17647 | F102: 425h/4,5p | G102: =(1*4.5)*(32.2)/(425)*(1000) -> 340.94118 | I102: 600h/3,5p | J102: =(1*3.5)*(32.2)/(600)*(1000) -> 187.83333
A103: 5001 a 25000 unid. | C103: 450h/3,5p | D103: =(1*3.5)*(32.2)/(450)*(1000) -> 250.44444 | F103: 450h/4,5p | G103: =(1*4.5)*(32.2)/(450)*(1000) -> 322 | I103: 650h/3,5p | J103: =(1*3.5)*(32.2)/(650)*(1000) -> 173.38462
A107: FRASCOS COSMETICA CAPACIDAD 600ML A 1000ML
C109: Etiquetado cilíndrico plastico | F109: Etiquetado cilíndrico vidrio | I109: Etiquetado plano plástico | L109: Etiquetado plano vidrio
A111: 500 unid. | C111: 2hx1,5p | D111: =(2*1.5)*(32.2)/(500)*(1000) -> 193.2 | F111: 2hx2,5p | G111: =(2*2.5)*(32.2)/(500)*(1000) -> 322 | I111: 2hx1,5p | J111: =(2*1.5)*(32.2)/(500)*(1000) -> 193.2 | L111: 2hx2,5p | M111: =(2*2.5)*(32.2)/(500)*(1000) -> 322
A112: 1000 unid. | C112: 3hx1,5p | D112: =(3*1.5)*(32.2)/(1000)*(1000) -> 144.9 | F112: 3hx2,5p | G112: =(3*2.5)*(32.2)/(1000)*(1000) -> 241.5 | I112: 3,5hx1,5p | J112: =(3.5*1.5)*(32.2)/(1000)*(1000) -> 169.05 | L112: 3,5hx2,5p | M112: =(3.5*2.5)*(32.2)/(1000)*(1000) -> 281.75
A113: 1500 a 2500 unid | C113: 550h/1,5p | D113: =(1*1.5)*(32.2)/(550)*(1000) -> 87.818182 | F113: 550h/2,5p | G113: =(1*2.5)*(32.2)/(550)*(1000) -> 146.36364 | I113: 450h/1,5p | J113: =(1*1.5)*(32.2)/(450)*(1000) -> 107.33333 | L113: 450h/2,5p | M113: =(1*2.5)*(32.2)/(450)*(1000) -> 178.88889
A114: 2501 a 5000 unid. | C114: 650h/1,5p | D114: =(1*1.5)*(32.2)/(650)*(1000) -> 74.307692 | F114: 650h/2,5p | G114: =(1*2.5)*(32.2)/(650)*(1000) -> 123.84615 | I114: 550h/1,5p | J114: =(1*1.5)*(32.2)/(550)*(1000) -> 87.818182 | L114: 550h/2,5p | M114: =(1*2.5)*(32.2)/(550)*(1000) -> 146.36364
A115: 5001 a 25000 unid. | C115: 800h/1,5p | D115: =(1*1.5)*(32.2)/(800)*(1000) -> 60.375 | F115: 800h/2,5p | G115: =(1*2.5)*(32.2)/(800)*(1000) -> 100.625 | I115: 700h/1,5p | J115: =(1*1.5)*(32.2)/(700)*(1000) -> 69 | L115: 700h/2,5p | M115: =(1*2.5)*(32.2)/(700)*(1000) -> 115
C118: Envasado | F118: Envasado + estuchado | I118: Estuchado
A120: 500 unid. | C120: 2,5h x 3,5p | D120: =(2.5*3.5)*(32.2)/(500)*(1000) -> 563.5 | F120: 2,5h x 4,5p | G120: =(2.5*4.5)*(32.2)/(500)*(1000) -> 724.5 | I120: 2h x 3,5p | J120: =(2*3.5)*(32.2)/(500)*(1000) -> 450.8
A121: 1000 unid. | C121: 3h x 3,5p | D121: =(3*3.5)*(32.2)/(1000)*(1000) -> 338.1 | F121: 3h x 4,5p | G121: =(3*4.5)*(32.2)/(1000)*(1000) -> 434.7 | I121: 2,5h x 3,5p | J121: =(2.5*3.5)*(32.2)/(1000)*(1000) -> 281.75
A122: 1500 a 2500 unid | C122: 375h/3,5p | D122: =(1*3.5)*(32.2)/(375)*(1000) -> 300.53333 | F122: 375h/4,5p | G122: =(1*4.5)*(32.2)/(375)*(1000) -> 386.4 | I122: 450h/3,5p | J122: =(1*3.5)*(32.2)/(450)*(1000) -> 250.44444
A123: 2501 a 5000 unid. | C123: 400h/3,5p | D123: =(1*3.5)*(32.2)/(400)*(1000) -> 281.75 | F123: 400h/4,5p | G123: =(1*4.5)*(32.2)/(400)*(1000) -> 362.25 | I123: 500h/3,5p | J123: =(1*3.5)*(32.2)/(500)*(1000) -> 225.4
A124: 5001 a 25000 unid. | C124: 425h/3,5p | D124: =(1*3.5)*(32.2)/(425)*(1000) -> 265.17647 | F124: 425h/4,5p | G124: =(1*4.5)*(32.2)/(425)*(1000) -> 340.94118 | I124: 550h/3,5p | J124: =(1*3.5)*(32.2)/(550)*(1000) -> 204.90909
E130: TARROS COSMETICA
A131: TARROS CAPACIDAD 200ML A 300ML
C133: Etiquetado cilíndrico plastico | F133: Etiquetado cilíndrico vidrio
A135: 500 unid. | C135: 1,5hx1,5p | D135: =(1.5*1.5)*(32.2)/(500)*(1000) -> 144.9 | F135: 1,5hx2,5p | G135: =(1.5*2.5)*(32.2)/(500)*(1000) -> 241.5
A136: 1000 unid. | C136: 2hx1,5p | D136: =(2*1.5)*(32.2)/(1000)*(1000) -> 96.6 | F136: 2hx2,5p | G136: =(2*2.5)*(32.2)/(1000)*(1000) -> 161
A137: 1500 a 2500 unid | C137: 650h/1,5p | D137: =(1*1.5)*(32.2)/(650)*(1000) -> 74.307692 | F137: 650h/2,5p | G137: =(1*2.5)*(32.2)/(650)*(1000) -> 123.84615
A138: 2501 a 5000 unid. | C138: 750h/1,5p | D138: =(1*1.5)*(32.2)/(750)*(1000) -> 64.4 | F138: 750h/2,5p | G138: =(1*2.5)*(32.2)/(750)*(1000) -> 107.33333
A139: 5001 a 25000 unid. | C139: 800h/1,5p | D139: =(1*1.5)*(32.2)/(800)*(1000) -> 60.375 | F139: 800h/2,5p | G139: =(1*2.5)*(32.2)/(800)*(1000) -> 100.625
C142: Envasado | F142: Envasado + estuchado | I142: Estuchado
A144: 500 unid. | C144: 2,5h x 3,5p | D144: =(2.5*3.5)*(32.2)/(500)*(1000) -> 563.5 | F144: 2,5h x 4,5p | G144: =(2.5*4.5)*(32.2)/(500)*(1000) -> 724.5 | I144: 1,5h x 3,5p | J144: =(1.5*3.5)*(32.2)/(500)*(1000) -> 338.1
A145: 1000 unid. | C145: 3h x 3,5p | D145: =(3*3.5)*(32.2)/(1000)*(1000) -> 338.1 | F145: 3h x 4,5p | G145: =(3*4.5)*(32.2)/(1000)*(1000) -> 434.7 | I145: 2h x 3,5p | J145: =(2*3.5)*(32.2)/(1000)*(1000) -> 225.4
A146: 1500 a 2500 unid | C146: 400h/3,5p | D146: =(1*3.5)*(32.2)/(400)*(1000) -> 281.75 | F146: 400h/4,5p | G146: =(1*4.5)*(32.2)/(400)*(1000) -> 362.25 | I146: 550h/3,5p | J146: =(1*3.5)*(32.2)/(550)*(1000) -> 204.90909
A147: 2501 a 5000 unid. | C147: 500h/3,5p | D147: =(1*3.5)*(32.2)/(500)*(1000) -> 225.4 | F147: 500h/4,5p | G147: =(1*4.5)*(32.2)/(500)*(1000) -> 289.8 | I147: 600h/3,5p | J147: =(1*3.5)*(32.2)/(600)*(1000) -> 187.83333
A148: 5001 a 25000 unid. | C148: 550h/3,5p | D148: =(1*3.5)*(32.2)/(550)*(1000) -> 204.90909 | F148: 550h/4,5p | G148: =(1*4.5)*(32.2)/(550)*(1000) -> 263.45455 | I148: 650h/3,5p | J148: =(1*3.5)*(32.2)/(650)*(1000) -> 173.38462
A152: TARROS CAPACIDAD 400ML A 500ML
C154: Etiquetado cilíndrico plastico | F154: Etiquetado cilíndrico vidrio
...

Sheet Tarifas Word Tubos (
B2: A PARTIR DE 75ml TIENE QUE IR BIEN COLOCADOS
B4: MAYENTIS TUBO 250Ml 3000 UNID. 218 € (2025)
B5: COSTE FIJO | D5: 375
B7: Capcidad (ml) | C7: Cantidad | D7: Precio (€) | E7: Precio unidad | F7: Elípticos | G7: Metálicos | H7: Pax adicional
B8: 250 | C8: 3000 | D8: 218 | E8: =+D8/C8 -> 0.072666667 | F8: =+D8*(1+0.85) -> 403.3 | G8: =+D8*(1+0.85) -> 403.3 | H8: 0.4
B9: 200 | C9: 1000 | D9: 375 | E9: =+D9/C9 -> 0.375 | F9: =+D9*(1+0.85) -> 693.75 | G9: =+D9*(1+0.85) -> 693.75 | H9: 0.4
B10: 200 | C10: 2000 | D10: 210 | E10: =+D10/C10 -> 0.105 | F10: =+D10*(1+0.85) -> 388.5 | G10: =+D10*(1+0.85) -> 388.5 | H10: 0.4
B11: 200 | C11: 2500 | D11: 156 | E11: =+D11/C11 -> 0.0624 | F11: =+D11*(1+0.85) -> 288.6 | G11: =+D11*(1+0.85) -> 288.6 | H11: 0.4
B12: 200 | C12: 5000 | D12: 146 | E12: =+D12/C12 -> 0.0292 | F12: =+D12*(1+0.85) -> 270.1 | G12: =+D12*(1+0.85) -> 270.1 | H12: 0.4
B13: 200 | C13: 10000 | D13: 127 | E13: =+D13/C13 -> 0.0127 | F13: =+D13*(1+0.85) -> 234.95 | G13: =+D13*(1+0.85) -> 234.95 | H13: 0.4
B14: 200 | C14: 20000 | D14: 112 | E14: =+D14/C14 -> 0.0056 | F14: =+D14*(1+0.85) -> 207.2 | G14: =+D14*(1+0.85) -> 207.2 | H14: 0.4
B15: 150 | C15: 1000 | D15: 375 | E15: =+D15/C15 -> 0.375 | F15: =+D15*(1+0.85) -> 693.75 | G15: =+D15*(1+0.85) -> 693.75 | H15: 0.4
B16: 150 | C16: 2000 | D16: 207 | E16: =+D16/C16 -> 0.1035 | F16: =+D16*(1+0.85) -> 382.95 | G16: =+D16*(1+0.85) -> 382.95 | H16: 0.4
B17: 150 | C17: 2500 | D17: 153 | E17: =+D17/C17 -> 0.0612 | F17: =+D17*(1+0.85) -> 283.05 | G17: =+D17*(1+0.85) -> 283.05 | H17: 0.4
B18: 150 | C18: 5000 | D18: 132 | E18: =+D18/C18 -> 0.0264 | F18: =+D18*(1+0.85) -> 244.2 | G18: =+D18*(1+0.85) -> 244.2 | H18: 0.4
B19: 150 | C19: 10000 | D19: 117 | E19: =+D19/C19 -> 0.0117 | F19: =+D19*(1+0.85) -> 216.45 | G19: =+D19*(1+0.85) -> 216.45 | H19: 0.4
... B21: 150 | C21: 50000 | D21: 96 | E21: =+D21/C21 -> 0.00192 | F21: =+D21*(1+0.85) -> 177.6 | G21: =+D21*(1+0.85) -> 177.6 | H21: 0.4
B22: 150 | C22: 100000 | D22: 89 | E22: =+D22/C22 -> 0.00089 | F22: =+D22*(1+0.75) -> 155.75 | G22: =+D22*(1+0.75) -> 155.75 | H22: 0.4
B23: 125 | C23: 1000 | D23: 375 | E23: =+D23/C23 -> 0.375 | F23: =+D23*(1+0.85) -> 693.75 | G23: =+D23*(1+0.85) -> 693.75 | H23: 0.4
B24: 125 | C24: 2000 | D24: 204 | E24: =+D24/C24 -> 0.102 | F24: =+D24*(1+0.85) -> 377.4 | G24: =+D24*(1+0.85) -> 377.4 | H24: 0.4
B25: 125 | C25: 2500 | D25: 149 | E25: =+D25/C25 -> 0.0596 | F25: =+D25*(1+0.85) -> 275.65 | G25: =+D25*(1+0.85) -> 275.65 | H25: 0.4
B26: 125 | C26: 5000 | D26: 127 | E26: =+D26/C26 -> 0.0254 | F26: =+D26*(1+0.85) -> 234.95 | G26: =+D26*(1+0.85) -> 234.95 | H26: 0.4
B27: 125 | C27: 10000 | D27: 115 | E27: =+D27/C27 -> 0.0115 | F27: =+D27*(1+0.85) -> 212.75 | G27: =+D27*(1+0.85) -> 212.75 | H27: 0.4
B28: 125 | C28: 20000 | D28: 102 | E28: =+D28/C28 -> 0.0051 | F28: =+D28*(1+0.85) -> 188.7 | G28: =+D28*(1+0.85) -> 188.7 | H28: 0.4
B29: 100 | C29: 1000 | D29: 375 | E29: =+D29/C29 -> 0.375 | F29: =+D29*(1+0.85) -> 693.75 | G29: =+D29*(1+0.85) -> 693.75 | H29: 0.4
B30: 100 | C30: 2000 | D30: 199 | E30: =+D30/C30 -> 0.0995 | F30: =+D30*(1+0.85) -> 368.15 | G30: =+D30*(1+0.85) -> 368.15 | H30: 0.4
B31: 100 | C31: 2500 | D31: 145 | E31: =+D31/C31 -> 0.058 | F31: =+D31*(1+0.85) -> 268.25 | G31: =+D31*(1+0.85) -> 268.25 | H31: 0.4
B32: 100 | C32: 5000 | D32: 120 | E32: =+D32/C32 -> 0.024 | F32: =+D32*(1+0.85) -> 222 | G32: =+D32*(1+0.85) -> 222 | H32: 0.4
B33: 100 | C33: 10000 | D33: 111 | E33: =+D33/C33 -> 0.0111 | F33: =+D33*(1+0.85) -> 205.35 | G33: =+D33*(1+0.85) -> 205.35 | H33: 0.4
B34: 100 | C34: 20000 | D34: 98 | E34: =+D34/C34 -> 0.0049 | F34: =+D34*(1+0.85) -> 181.3 | G34: =+D34*(1+0.85) -> 181.3 | H34: 0.4
B35: 100 | C35: 50000 | D35: 91 | E35: =+D35/C35 -> 0.00182 | F35: =+D35*(1+0.85) -> 168.35 | G35: =+D35*(1+0.85) -> 168.35 | H35: 0.4
B36: 100 | C36: 100000 | D36: 84 | E36: =+D36/C36 -> 0.00084 | F36: =+D36*(1+0.75) -> 147 | G36: =+D36*(1+0.75) -> 147 | H36: 0.4
B37: 75 | C37: 1000 | D37: 375 | E37: =+D37/C37 -> 0.375 | F37: =+D37*(1+0.85) -> 693.75 | G37: =+D37*(1+0.85) -> 693.75 | H37: 0.4
B38: 75 | C38: 2000 | D38: 193 | E38: =+D38/C38 -> 0.0965 | F38: =+D38*(1+0.85) -> 357.05 | G38: =+D38*(1+0.85) -> 357.05 | H38: 0.4
B39: 75 | C39: 2500 | D39: 140 | E39: =+D39/C39 -> 0.056 | F39: =+D39*(1+0.85) -> 259 | G39: =+D39*(1+0.85) -> 259 | H39: 0.4
B40: 75 | C40: 5000 | D40: 116 | E40: =+D40/C40 -> 0.0232 | F40: =+D40*(1+0.85) -> 214.6 | G40: =+D40*(1+0.85) -> 214.6 | H40: 0.4
B41: 75 | C41: 10000 | D41: 105 | E41: =+D41/C41 -> 0.0105 | F41: =+D41*(1+0.85) -> 194.25 | G41: =+D41*(1+0.85) -> 194.25 | H41: 0.4
B42: 75 | C42: 20000 | D42: 94 | E42: =+D42/C42 -> 0.0047 | F42: =+D42*(1+0.85) -> 173.9 | G42: =+D42*(1+0.85) -> 173.9 | H42: 0.4
B43: 75 | C43: 50000 | D43: 87 | E43: =+D43/C43 -> 0.00174 | F43: =+D43*(1+0.85) -> 160.95 | G43: =+D43*(1+0.85) -> 160.95 | H43: 0.4
B44: 75 | C44: 100000 | D44: 80 | E44: =+D44/C44 -> 0.0008 | F44: =+D44*(1+0.75) -> 140 | G44: =+D44*(1+0.75) -> 140 | H44: 0.4
B45: 50 | C45: 1000 | D45: 375 | E45: =+D45/C45 -> 0.375 | F45: =+D45*(1+0.85) -> 693.75 | G45: =+D45*(1+0.85) -> 693.75 | H45: 0.4
B46: 50 | C46: 2000 | D46: 193 | E46: =+D46/C46 -> 0.0965 | F46: =+D46*(1+0.85) -> 357.05 | G46: =+D46*(1+0.85) -> 357.05 | H46: 0.4
B47: 50 | C47: 2500 | D47: 140 | E47: =+D47/C47 -> 0.056 | F47: =+D47*(1+0.85) -> 259 | G47: =+D47*(1+0.85) -> 259 | H47: 0.4
B48: 50 | C48: 5000 | D48: 116 | E48: =+D48/C48 -> 0.0232 | F48: =+D48*(1+0.85) -> 214.6 | G48: =+D48*(1+0.85) -> 214.6 | H48: 0.4
B49: 50 | C49: 10000 | D49: 105 | E49: =+D49/C49 -> 0.0105 | F49: =+D49*(1+0.85) -> 194.25 | G49: =+D49*(1+0.85) -> 194.25 | H49: 0.4
B50: 50 | C50: 20000 | D50: 94 | E50: =+D50/C50 -> 0.0047 | F50: =+D50*(1+0.85) -> 173.9 | G50: =+D50*(1+0.85) -> 173.9 | H50: 0.4
B51: 50 | C51: 50000 | D51: 87 | E51: =+D51/C51 -> 0.00174 | F51: =+D51*(1+0.85) -> 160.95 | G51: =+D51*(1+0.85) -> 160.95 | H51: 0.4
B52: 50 | C52: 100000 | D52: 80 | E52: =+D52/C52 -> 0.0008 | F52: =+D52*(1+0.75) -> 140 | G52: =+D52*(1+0.75) -> 140 | H52: 0.4
B53: 30 | C53: 1000 | D53: 375 | E53: =+D53/C53 -> 0.375 | F53: =+D53*(1+0.85) -> 693.75 | G53: =+D53*(1+0.85) -> 693.75 | H53: 0.4
B54: 30 | C54: 2000 | D54: 188 | E54: =+D54/C54 -> 0.094 | F54: =+D54*(1+0.85) -> 347.8 | G54: =+D54*(1+0.85) -> 347.8 | H54: 0.4
B55: 30 | C55: 2500 | D55: 137 | E55: =+D55/C55 -> 0.0548 | F55: =+D55*(1+0.85) -> 253.45 | G55: =+D55*(1+0.85) -> 253.45 | H55: 0.4
B56: 30 | C56: 5000 | D56: 112 | E56: =+D56/C56 -> 0.0224 | F56: =+D56*(1+0.85) -> 207.2 | G56: =+D56*(1+0.85) -> 207.2 | H56: 0.4
B57: 30 | C57: 10000 | D57: 98 | E57: =+D57/C57 -> 0.0098 | F57: =+D57*(1+0.85) -> 181.3 | G57: =+D57*(1+0.85) -> 181.3 | H57: 0.4
B58: 30 | C58: 20000 | D58: 89 | E58: =+D58/C58 -> 0.00445 | F58: =+D58*(1+0.85) -> 164.65 | G58: =+D58*(1+0.85) -> 164.65 | H58: 0.4
B59: 30 | C59: 50000 | D59: 81 | E59: =+D59/C59 -> 0.00162 | F59: =+D59*(1+0.85) -> 149.85 | G59: =+D59*(1+0.85) -> 149.85 | H59: 0.4
B60: 30 | C60: 100000 | D60: 76 | E60: =+D60/C60 -> 0.00076 | F60: =+D60*(1+0.75) -> 133 | G60: =+D60*(1+0.75) -> 133 | H60: 0.4
B61: 15 | C61: 1000 | D61: 375 | E61: =+D61/C61 -> 0.375 | F61: =+D61*(1+0.85) -> 693.75 | G61: =+D61*(1+0.85) -> 693.75 | H61: 0.4
B62: 15 | C62: 2000 | D62: 188 | E62: =+D62/C62 -> 0.094 | F62: =+D62*(1+0.85) -> 347.8 | G62: =+D62*(1+0.85) -> 347.8 | H62: 0.4
B63: 15 | C63: 2500 | D63: 137 | E63: =+D63/C63 -> 0.0548 | F63: =+D63*(1+0.85) -> 253.45 | G63: =+D63*(1+0.85) -> 253.45 | H63: 0.4
B64: 15 | C64: 5000 | D64: 112 | E64: =+D64/C64 -> 0.0224 | F64: =+D64*(1+0.85) -> 207.2 | G64: =+D64*(1+0.85) -> 207.2 | H64: 0.4
B65: 15 | C65: 10000 | D65: 98 | E65: =+D65/C65 -> 0.0098 | F65: =+D65*(1+0.85) -> 181.3 | G65: =+D65*(1+0.85) -> 181.3 | H65: 0.4
B66: 15 | C66: 20000 | D66: 89 | E66: =+D66/C66 -> 0.00445 | F66: =+D66*(1+0.85) -> 164.65 | G66: =+D66*(1+0.85) -> 164.65 | H66: 0.4
B67: 15 | C67: 50000 | D67: 81 | E67: =+D67/C67 -> 0.00162 | F67: =+D67*(1+0.85) -> 149.85 | G67: =+D67*(1+0.85) -> 149.85 | H67: 0.4
B68: 15 | C68: 100000 | D68: 76 | E68: =+D68/C68 -> 0.00076 | F68: =+D68*(1+0.75) -> 133 | G68: =+D68*(1+0.75) -> 133 | H68: 0.4

Sheet tarifas Excel COPER
A1: M.P | B1: 5.12 | L1: 17 | N1: 210 | O1: 26 | R1: 239
A3: KG FAB. | B3: 50 | C3: 60 | D3: 70 | E3: 80 | F3: 90 | G3: 100 | H3: 125 | I3: 130 | J3: 140 | K3: 150 | L3: 160 | M3: 170 | N3: 180 | O3: 190 | P3: 200 | Q3: 210 | R3: 220
A4: TIEMPO
A5: PRECIO M.O. | B5: =(B4/60)*R1/B3 -> 0 | C5: =(C4/60)*R1/C3 -> 0 | D5: =(D4/60)*R1/D3 -> 0 | E5: =(E4/60)*R1/E3 -> 0 | F5: =(F4/60)*R1/F3 -> 0 | G5: =(G4/60)*R1/G3 -> 0 | H5: =(H4/60)*R1/H3 -> 0 | I5: =(I4/60)*R1/I3 -> 0 | J5: =(J4/60)*R1/J3 -> 0 | K5: =(K4/60)*R1/K3 -> 0 | L5: =(L4/60)*R1/L3 -> 0 | M5: =(M4/60)*R1/M3 -> 0 | N5: =(N4/60)*R1/N3 -> 0 | O5: =(O4/60)*R1/O3 -> 0 | P5: =(P4/60)*R1/P3 -> 0 | Q5: =(Q4/60)*R1/Q3 -> 0 | R5: =(R4/60)*R1/R3 -> 0
A6: ANALISIS 42€ | B6: =Q1/B3 -> 0 | C6: =Q1/C3 -> 0 | D6: =Q1/D3 -> 0 | E6: =Q1/E3 -> 0 | F6: =Q1/F3 -> 0 | G6: =Q1/G3 -> 0 | H6: =Q1/H3 -> 0 | I6: =Q1/I3 -> 0 | J6: =Q1/J3 -> 0 | K6: =Q1/K3 -> 0 | L6: =Q1/L3 -> 0 | M6: =Q1/M3 -> 0 | N6: =Q1/N3 -> 0 | O6: =Q1/O3 -> 0 | P6: =Q1/P3 -> 0 | Q6: =Q1/Q3 -> 0 | R6: =Q1/R3 -> 0
A7: ANALISIS 68€ | B7: =P1/B3 -> 0 | C7: =P1/C3 -> 0 | D7: =P1/D3 -> 0 | E7: =P1/E3 -> 0 | F7: =P1/F3 -> 0 | G7: =P1/G3 -> 0 | H7: =P1/H3 -> 0 | I7: =P1/I3 -> 0 | J7: =P1/J3 -> 0 | K7: =P1/K3 -> 0 | L7: =P1/L3 -> 0 | M7: =P1/M3 -> 0 | N7: =P1/N3 -> 0 | O7: =P1/O3 -> 0 | P7: =P1/P3 -> 0 | Q7: =P1/Q3 -> 0 | R7: =P1/R3 -> 0
A8: BIDON 100Kg. | B8: =O1/B3 -> 0.52 | C8: =O1/C3 -> 0.43333333 | D8: =O1/D3 -> 0.37142857 | E8: =P1/E3 -> 0 | F8: =O1/F3 -> 0.28888889 | G8: =O1/G3 -> 0.26 | H8: =O1*2/H3 -> 0.416 | I8: =O1*2/I3 -> 0.4 | J8: =O1*2/J3 -> 0.37142857 | K8: =O1*2/K3 -> 0.34666667 | L8: =O1*2/L3 -> 0.325 | M8: =O1*2/M3 -> 0.30588235 | N8: =O1*2/N3 -> 0.28888889 | O8: =O1*2/O3 -> 0.27368421 | P8: =O1*2/P3 -> 0.26 | Q8: =O1*2/Q3 -> 0.24761905 | R8: =O1*3/R3 -> 0.35454545
A9: BIDON 1000Kg.
A10: PALET EURO. | H10: =M1/H3 -> 0 | I10: =M1/I3 -> 0 | J10: =M1/J3 -> 0 | K10: =M1/K3 -> 0 | L10: =M1/L3 -> 0 | M10: =M1/M3 -> 0 | N10: =M1/N3 -> 0 | O10: =M1/O3 -> 0 | P10: =M1/P3 -> 0 | Q10: =M1/Q3 -> 0 | R10: =M1/R3 -> 0
A11: TRANSPORTE | H11: =L1/H3 -> 0.136 | I11: =L1/I3 -> 0.13076923 | J11: =L1/J3 -> 0.12142857 | K11: =L1/K3 -> 0.11333333 | L11: =L1/L3 -> 0.10625 | M11: =L1/M3 -> 0.1 | N11: =L1/N3 -> 0.094444444 | O11: =L1/O3 -> 0.089473684 | P11: =L1/P3 -> 0.085 | Q11: =L1/Q3 -> 0.080952381 | R11: =L1/R3 -> 0.077272727
A12: SUBTOTAL | B12: =SUM(B1+B5+B6+B7+B8) -> 5.64 | C12: =(B1+C5+C6+C7+C8+C9+C10+C11) -> 5.5533333 | D12: =(B1+D5+D6+D7+D8+D9+D10+D11) -> 5.4914286 | E12: =(B1+E5+E6+E7+E8+E9+E10+E11) -> 5.12 | F12: =(B1+F5+F6+F7+F8+F9+F10+F11) -> 5.4088889 | G12: =(B1+G5+G6+G7+G8+G9+G10+G11) -> 5.38 | H12: =(B1+H5+H6+H7+H8+H9+H10+H11) -> 5.672 | I12: =(B1+I5+I6+I7+I8+I9+I10+I11) -> 5.6507692 | J12: =(B1+J5+J6+J7+J8+J9+J10+J11) -> 5.6128571 | K12: =(B1+K5+K6+K7+K8+K9+K10+K11) -> 5.58 | L12: =(B1+L5+L6+L7+L8+L9+L10+L11) -> 5.55125 | M12: =(B1+M5+M6+M7+M8+M9+M10+M11) -> 5.5258824 | N12: =(B1+N5+N6+N7+N8+N9+N10+N11) -> 5.5033333 | O12: =(B1+O5+O6+O7+O8+O9+O10+O11) -> 5.4831579 | P12: =(B1+P5+P6+P7+P8+P9+P10+P11) -> 5.465 | Q12: =(B1+Q5+Q6+Q7+Q8+Q9+Q10+Q11) -> 5.4485714 | R12: =(B1+R5+R6+R7+R8+R9+R10+R11) -> 5.5518182
A13: MERMA 8% | B13: =(B12*8%) -> 0.4512 | C13: =(C12*8%) -> 0.44426667 | D13: =(D12*8%) -> 0.43931429
A14: MERMA 5% | E14: =E12*5% -> 0.256 | F14: =F12*5% -> 0.27044444 | G14: =G12*5% -> 0.269 | H14: =H12*5% -> 0.2836 | I14: =I12*5% -> 0.28253846 | J14: =J12*5% -> 0.28064286 | K14: =K12*5% -> 0.279 | L14: =L12*5% -> 0.2775625 | ... R14: =R12*5% -> 0.27759091
A15: TOTAL 1 | B15: =(B12+B13) -> 6.0912 | C15: =(C12+C13) -> 5.9976 | D15: =(D12+D13) -> 5.9307429 | E15: =(E12+E14) -> 5.376 | F15: =(F12+F14) -> 5.6793333 | G15: =G12+G14 -> 5.649 | H15: =H12+H14 -> 5.9556 | I15: =I12+I14 -> 5.9333077 | J15: =J12+J14 -> 5.8935 | K15: =K12+K14 -> 5.859 | L15: =L12+L14 -> 5.8288125 | M15: =M12+M14 -> 5.8021765 | N15: =N12+N14 -> 5.7785 | ... R15: =R12+R14 -> 5.8294091
A16: RESIDUOS | B16: =B15*2.5% -> 0.15228 | C16: =C15*2.5% -> 0.14994 | D16: =D15*2.5% -> 0.14826857 | E16: =E15*2.5% -> 0.1344 | F16: =F15*2.5% -> 0.14198333 | G16: =G15*2.5% -> 0.141225 | H16: =H15*2.5% -> 0.14889 | I16: =I15*2.5% -> 0.14833269 | J16: =J15*2.5% -> 0.1473375 | K16: =K15*3% -> 0.17577 | L16: =L15*2.5% -> 0.14572031 | M16: =M15*2.5% -> 0.14505441 | N16: =N15*2.5% -> 0.1444625 | O16: =O15*2.5% -> 0.14393289 | P16: =P15*2.5% -> 0.14345625 | Q16: =Q15*2.5% -> 0.143025 | R16: =R15*2.5% -> 0.14573523
A17: TOTAL 2 | B17: =(B15+B16) -> 6.24348 | C17: =(C15+C16) -> 6.14754 | D17: =(D15+D16) -> 6.0790114 | E17: =(E15+E16) -> 5.5104 | F17: =(F15+F16) -> 5.8213167 | G17: =(G15+G16) -> 5.790225 | H17: =(H15+H16) -> 6.10449 | I17: =(I15+I16) -> 6.0816404 | ... R17: =(R15+R16) -> 5.9751443
A20: KG FAB. | B20: 250 | C20: 275 | D20: 300 | E20: 340 | F20: 350 | G20: 375 | H20: 400 | I20: 430 | J20: 450 | K20: 475 | L20: 500 | M20: 525 | N20: 550 | O20: 575 | P20: 600 | Q20: 625 | R20: 650
A21: TIEMPO
A22: PRECIO M.O. | B22: =(B21/60)*R1/B20 -> 0 | C22: =(C21/60)*R1/C20 -> 0 | D22: =(D21/60)*R1/D20 -> 0 | E22: =(E21/60)*R1/E20 -> 0 | F22: =(F21/60)*R1/F20 -> 0 | G22: =(G21/60)*R1/G20 -> 0 | H22: =(H21/60)*R1/H20 -> 0 | I22: =(I21/60)*R1/I20 -> 0 | J22: =(J21/60)*R1/J20 -> 0 | K22: =(K21/60)*R1/K20 -> 0 | L22: =(L21/60)*R1/L20 -> 0 | M22: =(M21/60)*R1/M20 -> 0 | N22: =(N21/60)*R1/N20 -> 0 | O22: =(O21/60)*R1/O20 -> 0 | P22: =(P21/60)*R1/P20 -> 0 | Q22: =(Q21/60)*R1/Q20 -> 0 | R22: =(R21/60)*R1/R20 -> 0
A23: ANALISIS 42€ | B23: =Q1/B20 -> 0 | C23: =Q1/C20 -> 0 | D23: =Q1/D20 -> 0 | E23: =Q1/E20 -> 0 | F23: =Q1/F20 -> 0 | G23: =Q1/G20 -> 0 | H23: =Q1/H20 -> 0 | I23: =Q1/I20 -> 0 | J23: =Q1/J20 -> 0 | K23: =Q1/K20 -> 0 | L23: =Q1/L20 -> 0 | M23: =Q1/M20 -> 0 | N23: =Q1/N20 -> 0 | O23: =Q1/O20 -> 0 | P23: =Q1/P20 -> 0 | Q23: =Q1/Q20 -> 0 | R23: =Q1/R20 -> 0
A24: ANALISIS 68€ | B24: =P1/B20 -> 0 | C24: =P1/C20 -> 0 | D24: =P1/D20 -> 0 | E24: =P1/E20 -> 0 | F24: =P1/F20 -> 0 | G24: =P1/G20 -> 0 | H24: =P1/H20 -> 0 | I24: =P1/I20 -> 0 | J24: =P1/J20 -> 0 | K24: =P1/K20 -> 0 | L24: =P1/L20 -> 0 | M24: =P1/M20 -> 0 | N24: =P1/N20 -> 0 | O24: =P1/O20 -> 0 | P24: =P1/P20 -> 0 | Q24: =P1/Q20 -> 0 | R24: =P1/R20 -> 0
A25: BIDON 100Kg. | B25: =O1*3/B20 -> 0.312 | C25: =O1*3/C20 -> 0.28363636 | D25: =O1*3/D20 -> 0.26 | E25: =O1*4/E20 -> 0.30588235 | F25: =O1*4/F20 -> 0.29714286 | G25: =O1*4/G20 -> 0.27733333 | H25: =O1*4/H20 -> 0.26 | K25: =O1*5/K20 -> 0.27368421 | M25: =O1*5/M20 -> 0.24761905 | N25: =O1*6/N20 -> 0.28363636 | O25: =O1*6/O20 -> 0.27130435 | P25: =O1*6/P20 -> 0.26 | Q25: =O1*6/Q20 -> 0.2496 | R25: =O1*7/R20 -> 0.28
A26: BIDON 1000Kg. | I26: =M3/I20 -> 0.39534884 | J26: =N1/J20 -> 0.46666667 | L26: =N1/L20 -> 0.42
A27: PALET EURO. | B27: =M1/B20 -> 0 | C27: =M1/C20 -> 0 | D27: =M1/D20 -> 0 | E27: =M1/E20 -> 0 | F27: =M1*2/F20 -> 0 | G27: =M1*2/G20 -> 0 | H27: =M1*2/H20 -> 0 | I27: =M1*2/I20 -> 0 | J27: =M1*2/J20 -> 0 | K27: =M1*2/K20 -> 0 | L27: =M1*2/L20 -> 0 | M27: =M1*2/M20 -> 0 | N27: =M1*2/N20 -> 0 | O27: =M1*2/O20 -> 0 | P27: =M1*2/P20 -> 0 | Q27: =M1*2/Q20 -> 0 | R27: =M1*3/R20 -> 0
A28: TRANSPORTE | B28: =L1/B20 -> 0.068 | C28: =L1/C20 -> 0.061818182 | D28: =L1/D20 -> 0.056666667 | E28: =L1*2/E20 -> 0.1 | F28: =L1*2/F20 -> 0.097142857 | G28: =L1*2/G20 -> 0.090666667 | H28: =L1*2/H20 -> 0.085 | I28: =L1/I20 -> 0.039534884 | J28: =L1/J20 -> 0.037777778 | K28: =L1*2/K20 -> 0.071578947 | L28: =L1/L20 -> 0.034 | M28: =L1*2/M20 -> 0.064761905 | N28: =L1*2/N20 -> 0.061818182 | O28: =L1*2/O20 -> 0.059130435 | P28: =L1*2/P20 -> 0.056666667 | Q28: =L1*2/Q20 -> 0.0544 | R28: =L1*2/R20 -> 0.052307692
A29: SUBTOTAL | B29: =B1+B22+B23+B24+B25+B26+B27+B28 -> 5.5 | C29: =B1+C22+C23+C24+C25+C26+C27+C28 -> 5.4654545 | D29: =B1+D22+D23+D24+D25+D26+D27+D28 -> 5.4366667 | E29: =B1+E22+E23+E24+E25+E26+E27+E28 -> 5.5258824 | F29: =B1+F22+F23+F24+F25+F26+F27+F28 -> 5.5142857 | G29: =B1+G22+G23+G24+G25+G26+G27+G28 -> 5.488 | H29: =B1+H22+H23+H24+H25+H26+H27+H28 -> 5.465 | I29: =B1+I22+I23+I24+I25+I26+I27+I28 -> 5.5548837 | J29: =B1+J22+J23+J24+J25+J26+J27+J28 -> 5.6244444 | K29: =B1+K22+K23+K24+K25+K26+K27+K28 -> 5.4652632 | L29: =B1+L22+L23+L24+L25+L26+L27+L28 -> 5.574 | M29: =B1+M22+M23+M24+M25+M26+M27+M28 -> 5.432381 | N29: =B1+N22+N23+N24+N25+N26+N27+N28 -> 5.4654545 | O29: =B1+O22+O23+O24+O25+O26+O27+O28 -> 5.4504348 | P29: =B1+P22+P23+P24+P25+P26+P27+P28 -> 5.4366667 | Q29: =B1+Q22+Q23+Q24+Q25+Q26+Q27+Q28 -> 5.424 | R29: =B1+R22+R23+R24+R25+R26+R27+R28 -> 5.4523077
A30: MERMA 8%
A31: MERMA 5% | B31: =B29*5% -> 0.275 | C31: =C29*5% -> 0.27327273 | D31: =D29*5% -> 0.27183333 | E31: =E29*5% -> 0.27629412 | F31: =F29*5% -> 0.27571429 | G31: =G29*5% -> 0.2744 | H31: =H29*5% -> 0.27325 | I31: =I29*5% -> 0.27774419 | ... R31: =R29*5% -> 0.27261538
A32: TOTAL 1 | B32: =SUM(B29:B31) -> 5.775 | C32: =SUM(C29:C31) -> 5.7387273 | D32: =SUM(D29:D31) -> 5.7085 | E32: =SUM(E29:E31) -> 5.8021765 | F32: =SUM(F29:F31) -> 5.79 | G32: =SUM(G29:G31) -> 5.7624 | H32: =SUM(H29:H31) -> 5.73825 | I32: =SUM(I29:I31) -> 5.8326279 | ... R32: =SUM(R29:R31) -> 5.7249231
A33: RESIDUOS | B33: =B32*2.5% -> 0.144375 | C33: =C32*2.5% -> 0.14346818 | D33: =D32*2.5% -> 0.1427125 | E33: =E32*2.5% -> 0.14505441 | F33: =F32*2.5% -> 0.14475 | G33: =G32*2.5% -> 0.14406 | H33: =H32*2.5% -> 0.14345625 | I33: =I32*2.5% -> 0.1458157 | ... K33: =K32*2.5% -> 0.14346316 | L33: =L32*3% -> 0.175581 | M33: =M32*2.5% -> 0.1426 | N33: =N32*2.5% -> 0.14346818 | O33: =O32*2.5% -> 0.14307391 | P33: =P32*2.5% -> 0.1427125 | Q33: =Q32*2.5% -> 0.14238 | R33: =R32*2.5% -> 0.14312308
A34: TOTAL 2 | B34: =SUM(B32:B33) -> 5.919375 | C34: =SUM(C32:C33) -> 5.8821955 | D34: =SUM(D32:D33) -> 5.8512125 | E34: =SUM(E32:E33) -> 5.9472309 | F34: =SUM(F32:F33) -> 5.93475 | G34: =SUM(G32:G33) -> 5.90646 | H34: =SUM(H32:H33) -> 5.8817062 | I34: =SUM(I32:I33) -> 5.9784436 | ... R34: =SUM(R32:R33) -> 5.8680462
A35: M.P | B35: =B1 -> 5.12 | C35: =C1 -> 0 | L35: =L1 -> 17 | N35: =N1 -> 210 | O35: =O1 -> 26 | R35: =R1 -> 239
A37: KG FAB. | B37: 675 | C37: 700 | D37: 725 | E37: 750 | F37: 775 | G37: 800 | H37: 850 | I37: 900 | J37: 950 | K37: 1000 | L37: 1050 | M37: 1100 | N37: 1150 | O37: 1200 | P37: 1250 | Q37: 1300 | R37: 1350
A38: TIEMPO
A39: PRECIO M.O. | B39: =(B38/60)*R1/B37 -> 0 | C39: =(C38/60)*R1/C37 -> 0 | D39: =(D38/60)*R1/D37 -> 0 | E39: =(E38/60)*R1/E37 -> 0 | F39: =(F38/60)*R1/F37 -> 0 | G39: =(G38/60)*R1/G37 -> 0 | H39: =(H38/60)*R1/H37 -> 0 | I39: =(I38/60)*R1/I37 -> 0 | J39: =(J38/60)*R1/J37 -> 0 | K39: =(K38/60)*R1/K37 -> 0 | L39: =(L38/60)*R1/L37 -> 0 | M39: =(M38/60)*R1/M37 -> 0 | N39: =(N38/60)*R1/N37 -> 0 | O39: =(O38/60)*R1/O37 -> 0 | P39: =(P38/60)*R1/P37 -> 0 | Q39: =(Q38/60)*R1/Q37 -> 0 | R39: =(R38/60)*R1/R37 -> 0
A40: ANALISIS 42€ | B40: =Q1/B37 -> 0 | C40: =Q1/C37 -> 0 | D40: =Q1/D37 -> 0 | E40: =Q1/E37 -> 0 | F40: =Q1/F37 -> 0 | G40: =Q1/G37 -> 0 | H40: =Q1/H37 -> 0 | I40: =Q1/I37 -> 0 | J40: =Q1/J37 -> 0 | K40: =Q1/K37 -> 0 | L40: =Q1/L37 -> 0 | M40: =Q1/M37 -> 0 | N40: =Q1/N37 -> 0 | O40: =Q1/O37 -> 0 | P40: =Q1/P37 -> 0 | Q40: =Q1/Q37 -> 0 | R40: =Q1/R37 -> 0
A41: ANALISIS 68€ | B41: =P1/B37 -> 0 | C41: =P1/C37 -> 0 | D41: =P1/D37 -> 0 | E41: =P1/E37 -> 0 | F41: =P1/F37 -> 0 | G41: =P1/G37 -> 0 | H41: =P1/H37 -> 0 | I41: =P1/I37 -> 0 | J41: =P1/J37 -> 0 | K41: =P1/K37 -> 0 | L41: =P1/L37 -> 0 | M41: =P17/M37 -> 0.0053470057 | N41: =P1/N37 -> 0 | O41: =P1/O37 -> 0 | P41: =P1/P37 -> 0 | Q41: =P1/Q37 -> 0 | R41: =P1/R37 -> 0
A42: BIDON 100Kg. | D42: =O1*8/D37 -> 0.28689655 | E42: =O1*8/E37 -> 0.27733333 | F42: =O1*8/F37 -> 0.2683871 | H42: =O1*9/H37 -> 0.27529412 | I42: =O1*9/I37 -> 0.26 | J42: =O1*10/J37 -> 0.27368421 | L42: =O1*11/L37 -> 0.27238095 | M42: =O1*11/M37 -> 0.26 | N42: =O1*12/N37 -> 0.27130435 | O42: =O1*12/O37 -> 0.26 | P42: =O1*13/P37 -> 0.2704 | Q42: =O1*13/Q37 -> 0.26 | R42: =O1*14/R37 -> 0.26962963
A43: BIDON 1000Kg. | B43: =N35/B37 -> 0.31111111 | C43: =N35/C37 -> 0.3 | G43: =N35/G37 -> 0.2625 | K43: =N35/K37 -> 0.21
A44: PALET EURO. | B44: =M1/B37 -> 0 | C44: =M1/C37 -> 0 | D44: =M1/D37 -> 0 | E44: =M1/E37 -> 0 | F44: =M1*2/F37 -> 0 | G44: =M1*2/G37 -> 0 | H44: =M1*2/H37 -> 0 | I44: =M1*2/I37 -> 0 | J44: =M1*2/J37 -> 0 | K44: =M1*2/K37 -> 0 | L44: =M1*2/L37 -> 0 | M44: =M1*2/M37 -> 0 | N44: =M1*2/N37 -> 0 | O44: =M1*2/O37 -> 0 | P44: =M1*2/P37 -> 0 | Q44: =M1*2/Q37 -> 0 | R44: =M1*3/R37 -> 0
A45: TRANSPORTE | B45: =L1/B37 -> 0.025185185 | C45: =L1/C37 -> 0.024285714 | D45: =L1/D37 -> 0.023448276 | E45: =L1*3/E37 -> 0.068 | F45: =L1*2/F37 -> 0.043870968 | G45: =L1*2/G37 -> 0.0425 | H45: =L1*2/H37 -> 0.04 | I45: =L1*2/I37 -> 0.037777778 | J45: =L1*2/J37 -> 0.035789474 | K45: =L1/K37 -> 0.017 | L45: =L1*2/L37 -> 0.032380952 | M45: =L1*2/M37 -> 0.030909091 | N45: =L1*2/N37 -> 0.029565217 | O45: =L1*2/O37 -> 0.028333333 | P45: =L1*2/P37 -> 0.0272 | Q45: =L1*2/Q37 -> 0.026153846 | R45: =L1*2/R37 -> 0.025185185
A46: SUBTOTAL | B46: =SUM(B35+B39+B40+B41+B42+B43+B44+B45) -> 5.4562963 | C46: =SUM(B35+C39+C40+C41+C42+C43+C44+C45) -> 5.4442857 | D46: =B35+D39+D40+D41+D42+D43+D44+D45 -> 5.4303448 | E46: =B35+E39+E40+E41+E42+E43+E44+E45 -> 5.4653333 | F46: =B35+F39+F40+F41+F42+F43+F44+F45 -> 5.4322581 | G46: =B35+G39+G40+G41+G42+G43+G44+G45 -> 5.425 | H46: =B35+H39+H40+H41+H42+H43+H44+H45 -> 5.4352941 | I46: =B35+I39+I40+I41+I42+I43+I44+I45 -> 5.4177778 | J46: =B35+J39+J40+J41+J42+J43+J44+J45 -> 5.4294737 | K46: =B35+K39+K40+K41+K42+K43+K44+K45 -> 5.347 | L46: =B35+L39+L40+L41+L42+L43+L44+L45 -> 5.4247619 | M46: =B35+M39+M40+M41+M42+M43+M44+M45 -> 5.4162561 | N46: =B35+N39+N40+N41+N42+N43+N44+N45 -> 5.4208696 | O46: =B35+O39+O40+O41+O42+O43+O44+O45 -> 5.4083333 | P46: =B35+P39+P40+P41+P42+P43+P44+P45 -> 5.4176 | Q46: =B35+Q39+Q40+Q41+Q42+Q43+Q44+Q45 -> 5.4061538 | R46: =B35+R39+R40+R41+R42+R43+R44+R45 -> 5.4148148
A47: MERMA 8%
A48: MERMA 5% | B48: =B46*5% -> 0.27281481 | C48: =C46*5% -> 0.27221429 | D48: =D46*5% -> 0.27151724 | E48: =E46*5% -> 0.27326667 | F48: =F46*5% -> 0.2716129 | G48: =G46*5% -> 0.27125 | H48: =H46*5% -> 0.27176471 | I48: =I46*5% -> 0.27088889 | ... R48: =R46*5% -> 0.27074074
A49: TOTAL 1 | B49: =(B46+B48) -> 5.7291111 | C49: =(C46+C48) -> 5.7165 | D49: =(D46+D48) -> 5.7018621 | E49: =(E46+E48) -> 5.7386 | F49: =(F46+F48) -> 5.703871 | G49: =G46+G48 -> 5.69625 | H49: =H46+H48 -> 5.7070588 | I49: =I46+I48 -> 5.6886667 | J49: =J46+J48 -> 5.7009474 | K49: =K46+K48 -> 5.61435 | L49: =L46+L48 -> 5.696 | M49: =M46+M48 -> 5.6870689 | N49: =N46+N48 -> 5.691913 | ... R49: =R46+R48 -> 5.6855556
A50: RESIDUOS | B50: =B49*2.5% -> 0.14322778 | C50: =C49*2.5% -> 0.1429125 | D50: =D49*2.5% -> 0.14254655 | E50: =E49*2.5% -> 0.143465 | F50: =F49*2.5% -> 0.14259677 | G50: =G49*2.5% -> 0.14240625 | H50: =H49*2.5% -> 0.14267647 | I50: =I49*2.5% -> 0.14221667 | J50: =J49*2.5% -> 0.14252368 | K50: =K49*3% -> 0.1684305 | L50: =L49*2.5% -> 0.1424 | M50: =M49*2.5% -> 0.14217672 | N50: =N49*2.5% -> 0.14229783 | O50: =O49*2.5% -> 0.14196875 | P50: =P49*2.5% -> 0.142212 | Q50: =Q49*2.5% -> 0.14191154 | R50: =R49*2.5% -> 0.14213889
A51: TOTAL 2 | B51: =(B49+B50) -> 5.8723389 | C51: =(C49+C50) -> 5.8594125 | D51: =(D49+D50) -> 5.8444086 | E51: =(E49+E50) -> 5.882065 | F51: =(F49+F50) -> 5.8464677 | G51: =(G49+G50) -> 5.8386563 | H51: =(H49+H50) -> 5.8497353 | I51: =(I49+I50) -> 5.8308833 | ... R51: =(R49+R50) -> 5.8276944
A54: KG FAB. | B54: 1400 | C54: 1450 | D54: 1500 | E54: 1550 | F54: 1600 | G54: 1650 | H54: 1700 | I54: 1750 | J54: 1800 | K54: 1850 | L54: 1900 | M54: 1950 | N54: 2000 | O54: 2050 | P54: 2100 | Q54: 2150 | R54: 2200
A55: TIEMPO
A56: PRECIO M.O. | B56: =(B55/60)*R1/B54 -> 0 | C56: =(C55/60)*R1/C54 -> 0 | D56: =(D55/60)*R1/D54 -> 0 | E56: =(E55/60)*R1/E54 -> 0 | F56: =(F55/60)*R1/F54 -> 0 | G56: =(G55/60)*R1/G54 -> 0 | H56: =(H55/60)*R1/H54 -> 0 | I56: =(I55/60)*R1/I54 -> 0 | J56: =(J55/60)*R1/J54 -> 0 | K56: =(K55/60)*R1/K54 -> 0 | L56: =(L55/60)*R1/L54 -> 0 | M56: =(M55/60)*R1/M54 -> 0 | N56: =(N55/60)*R1/N54 -> 0 | O56: =(O55/60)*R1/O54 -> 0 | P56: =(P55/60)*R1/P54 -> 0 | Q56: =(Q55/60)*R1/Q54 -> 0 | R56: =(R55/60)*R1/R54 -> 0
A57: ANALISIS 42€ | B57: =Q35/B54 -> 0 | C57: =Q35/C54 -> 0 | D57: =Q35/D54 -> 0 | E57: =Q35/E54 -> 0 | F57: =Q35/F54 -> 0 | G57: =Q35/G54 -> 0 | H57: =Q35/H54 -> 0 | I57: =Q35/I54 -> 0 | J57: =Q35/J54 -> 0 | K57: =Q35/K54 -> 0 | L57: =Q35/L54 -> 0 | M57: =Q35/M54 -> 0 | N57: =Q35/N54 -> 0 | O57: =Q35/O54 -> 0 | P57: =Q35/P54 -> 0 | Q57: =Q35/Q54 -> 0 | R57: =Q35/R54 -> 0
A58: ANALISIS 68€ | B58: =P35/B54 -> 0 | C58: =P35/C54 -> 0 | D58: =P35/D54 -> 0 | E58: =P35/E54 -> 0 | F58: =P35/F54 -> 0 | G58: =P35/G54 -> 0 | H58: =P35/H54 -> 0 | I58: =P35/I54 -> 0 | J58: =P35/J54 -> 0 | K58: =P35/K54 -> 0 | L58: =P35/L54 -> 0 | M58: =P35/M54 -> 0 | N58: =P35/N54 -> 0 | O58: =P35/O54 -> 0 | P58: =P35/P54 -> 0 | Q58: =P35/Q54 -> 0 | R58: =P35/R54 -> 0
A59: BIDON 100Kg. | B59: =O35*14/B54 -> 0.26 | C59: =O35*15/C54 -> 0.26896552 | E59: =O35*16/E54 -> 0.2683871 | F59: =O35*16/F54 -> 0.26 | G59: =O35*17/G54 -> 0.26787879 | H59: =O35*17/H54 -> 0.26 | I59: =O35*18/I54 -> 0.26742857 | J59: =O35*18/J54 -> 0.26 | K59: =O35*19/K54 -> 0.26702703 | L59: =O35*19/L54 -> 0.26 | M59: =O35*20/M54 -> 0.26666667 | N59: =O35*20/N54 -> 0.26 | O59: =O35*21/O54 -> 0.26634146 | P59: =O35*6/P54 -> 0.074285714 | Q59: =O35*6/Q54 -> 0.07255814 | R59: =O35*7/R54 -> 0.082727273
A60: BIDON 1000Kg. | D60: =N35*2/D54 -> 0.28
A61: PALET EURO. | B61: =M34/B54 -> 0.0041761429 | C61: =M34/C54 -> 0.0040321379 | D61: =M34/D54 -> 0.0038977333 | E61: =M34/E54 -> 0.003772 | F61: =M35*2/F54 -> 0 | G61: =M34*2/G54 -> 0.0070867879 | H61: =M34*2/H54 -> 0.0068783529 | I61: =M34*2/I54 -> 0.0066818286 | J61: =M34*2/J54 -> 0.0064962222 | K61: =M34*2/K54 -> 0.0063206486 | L61: =M34*2/L54 -> 0.0061543158 | M61: =M34*2/M54 -> 0.0059965128 | N61: =M34*2/N54 -> 0.0058466 | O61: =M34*2/O54 -> 0.005704 | P61: =M34*2/P54 -> 0.0055681905 | Q61: =M34*2/Q54 -> 0.0054386977 | R61: =M34*3/R54 -> 0.0079726364
A62: TRANSPORTE | B62: =L35/B54 -> 0.012142857 | C62: =L35/C54 -> 0.011724138 | D62: =L35*2/D54 -> 0.022666667 | E62: =L35/E54 -> 0.010967742 | F62: =L35*2/F54 -> 0.02125 | G62: =L35*2/G54 -> 0.020606061 | H62: =L35*2/H54 -> 0.02 | I62: =L35*2/I54 -> 0.019428571 | J62: =L35*2/J54 -> 0.018888889 | K62: =L35*2/K54 -> 0.018378378 | L62: =L35*2/L54 -> 0.017894737 | M62: =L35*2/M54 -> 0.017435897 | N62: =L35*2/N54 -> 0.017 | O62: =L35*2/O54 -> 0.016585366 | P62: =L35*2/P54 -> 0.016190476 | Q62: =L35*2/Q54 -> 0.015813953 | R62: =L35*2/R54 -> 0.015454545
A63: SUBTOTAL | B63: =B35+B56+B57+B58+B59+B60+B61+B62 -> 5.396319 | C63: =B35+C56+C57+C58+C59+C60+C61+C62 -> 5.4047218 | D63: =B35+D56+D57+D58+D59+D60+D61+D62 -> 5.4265644 | E63: =B35+E56+E57+E58+E59+E60+E61+E62 -> 5.4031268 | F63: =B35+F56+F57+F58+F59+F60+F61+F62 -> 5.40125 | G63: =B35+G56+G57+G58+G59+G60+G61+G62 -> 5.4155716 | H63: =B35+H56+H57+H58+H59+H60+H61+H62 -> 5.4068784 | I63: =B35+I56+I57+I58+I59+I60+I61+I62 -> 5.413539 | J63: =B35+J56+J57+J58+J59+J60+J61+J62 -> 5.4053851 | K63: =B35+K56+K57+K58+K59+K60+K61+K62 -> 5.4117261 | L63: =B35+L56+L57+L58+L59+L60+L61+L62 -> 5.4040491 | M63: =B35+M56+M57+M58+M59+M60+M61+M62 -> 5.4100991 | N63: =B35+N56+N57+N58+N59+N60+N61+N62 -> 5.4028466 | O63: =B35+O56+O57+O58+O59+O60+O61+O62 -> 5.4086308 | P63: =B35+P56+P57+P58+P59+P60+P61+P62 -> 5.2160444 | Q63: =B35+Q56+Q57+Q58+Q59+Q60+Q61+Q62 -> 5.2138108 | R63: =B35+R56+R57+R58+R59+R60+R61+R62 -> 5.2261545
A64: MERMA 8%
A65: MERMA 5% | B65: =B63*5% -> 0.26981595 | C65: =C63*5% -> 0.27023609 | D65: =D63*5% -> 0.27132822 | E65: =E63*5% -> 0.27015634 | F65: =F63*5% -> 0.2700625 | G65: =G63*5% -> 0.27077858 | H65: =H63*5% -> 0.27034392 | I65: =I63*5% -> 0.27067695 | ... R65: =R63*5% -> 0.26130772
A66: TOTAL 1 | B66: =(B63+B65) -> 5.666135 | C66: =(C63+C65) -> 5.6749579 | D66: =(D63+D65) -> 5.6978926 | E66: =(E63+E65) -> 5.6732832 | F66: =(F63+F65) -> 5.6713125 | G66: =G63+G65 -> 5.6863502 | H66: =H63+H65 -> 5.6772223 | I66: =I63+I65 -> 5.6842159 | J66: =J63+J65 -> 5.6756544 | K66: =K63+K65 -> 5.6823124 | L66: =L63+L65 -> 5.6742515 | M66: =M63+M65 -> 5.680604 | N66: =N63+N65 -> 5.6729889 | ... R66: =R63+R65 -> 5.4874622
A67: RESIDUOS | B67: =B66*2.5% -> 0.14165337 | C67: =C66*2.5% -> 0.14187395 | D67: =D66*3% -> 0.17093678 | E67: =E66*2.5% -> 0.14183208 | F67: =F66*2.5% -> 0.14178281 | G67: =G66*2.5% -> 0.14215876 | H67: =H66*2.5% -> 0.14193056 | I67: =I66*2.5% -> 0.1421054 | J67: =J66*2.5% -> 0.14189136 | K67: =K66*2.5% -> 0.14205781 | L67: =L66*2.5% -> 0.14185629 | ... R67: =R66*2.5% -> 0.13718655
A68: TOTAL 2 | B68: =(B66+B67) -> 5.8077883 | C68: =(C66+C67) -> 5.8168318 | D68: =(D66+D67) -> 5.8688294 | E68: =(E66+E67) -> 5.8151153 | F68: =(F66+F67) -> 5.8130953 | G68: =(G66+G67) -> 5.828509 | H68: =(H66+H67) -> 5.8191528 | I68: =(I66+I67) -> 5.8263213 | ... R68: =(R66+R67) -> 5.6246487
A69: M.P | B69: =B1 -> 5.12 | C69: =C1 -> 0 | L69: =L1 -> 17 | N69: =N1 -> 210 | O69: =O1 -> 26 | P69: =P1 -> 0 | Q69: =Q1 -> 0 | R69: =R35 -> 239
A70: PRECIOS KG
A71: KG FAB. | B71: 2250 | C71: 2300 | D71: 2350 | E71: 2400 | F71: 2450 | G71: 2500 | H71: 2550 | I71: 2600 | J71: 2650 | K71: 2700 | L71: 2750 | M71: 2800 | N71: 2850 | O71: 2900 | P71: 2950 | Q71: 3000 | R71: 3100
A72: TIEMPO | Q72: 675
A73: PRECIO M.O. | B73: =(B72/60)*R1/B71 -> 0 | C73: =(C72/60)*R69/C71 -> 0 | D73: =(D72/60)*R69/D71 -> 0 | E73: =(E72/60)*R69/E71 -> 0 | F73: =(F72/60)*R69/F71 -> 0 | G73: =(G72/60)*R69/G71 -> 0 | H73: =(H72/60)*R69/H71 -> 0 | I73: =(I72/60)*R69/I71 -> 0 | J73: =(J72/60)*R69/J71 -> 0 | K73: =(K72/60)*R69/K71 -> 0 | L73: =(L72/60)*R69/L71 -> 0 | M73: =(M72/60)*R69/M71 -> 0 | N73: =(N72/60)*R69/N71 -> 0 | O73: =(O72/60)*R69/O71 -> 0 | P73: =(P72/60)*R69/P71 -> 0 | Q73: =(Q72/60)*R69/Q71 -> 0.89625 | R73: =(R72/60)*R69/R71 -> 0
A74: ANALISIS 42€ | B74: =Q69/B71 -> 0 | C74: =Q69/C71 -> 0 | D74: =Q69/D71 -> 0 | E74: =Q69/E71 -> 0 | F74: =Q69/F71 -> 0 | G74: =Q69/G71 -> 0 | H74: =Q69/H71 -> 0 | I74: =Q69/I71 -> 0 | J74: =Q69/J71 -> 0 | K74: =Q69/K71 -> 0 | L74: =Q69/L71 -> 0 | M74: =Q69*3/M71 -> 0 | N74: =Q69/N71 -> 0 | O74: =Q69/O71 -> 0 | P74: =Q69/P71 -> 0 | Q74: =Q69/Q71 -> 0 | R74: =Q69/R71 -> 0
A75: ANALISIS 68€ | B75: =P69/B71 -> 0 | C75: =P69/C71 -> 0 | D75: =P69/D71 -> 0 | E75: =P69/E71 -> 0 | F75: =P69/F71 -> 0 | G75: =P69/G71 -> 0 | H75: =P69/H71 -> 0 | I75: =P69/I71 -> 0 | J75: =P69/J71 -> 0 | K75: =P69/K71 -> 0 | L75: =P69/L71 -> 0 | M75: =P69*3/M71 -> 0 | N75: =P69/N71 -> 0 | O75: =P69/O71 -> 0 | P75: =P69/P71 -> 0 | Q75: =P69/Q71 -> 0 | R75: =P69/R71 -> 0
A76: BIDON 100Kg. | B76: =O69*3/B71 -> 0.034666667 | C76: =O69*3/C71 -> 0.033913043 | D76: =O69*3/D71 -> 0.033191489 | E76: =O69*3/E71 -> 0.0325 | F76: =O69*4/F71 -> 0.04244898 | H76: =O69*4/H71 -> 0.040784314 | I76: =O69*4/I71 -> 0.04 | J76: =O69*5/J71 -> 0.049056604 | K76: =O69*5/K71 -> 0.048148148 | L76: =O69*5/L71 -> 0.047272727 | N76: =O69*6/N71 -> 0.054736842 | O76: =O69*6/O71 -> 0.053793103 | P76: =O69*6/P71 -> 0.052881356 | R76: =O69*7/R71 -> 0.058709677
A77: BIDON 1000Kg. | G77: =N69*3/G71 -> 0.252 | M77: =N69*3/M71 -> 0.225 | Q77: =N69*3/Q71 -> 0.21
A78: PALET EURO. | B78: =M69/B71 -> 0 | C78: =M69/C71 -> 0 | D78: =M69/D71 -> 0 | E78: =M69/E71 -> 0 | F78: =M69*2/F71 -> 0 | G78: =M69*2/G71 -> 0 | H78: =M69*2/H71 -> 0 | I78: =M69*2/I71 -> 0 | J78: =M69*2/J71 -> 0 | K78: =M69*2/K71 -> 0 | L78: =M69*2/L71 -> 0 | M78: =M69*2/M71 -> 0 | N78: =M69*2/N71 -> 0 | O78: =M69*2/O71 -> 0 | P78: =M69*2/P71 -> 0 | Q78: =M69*2/Q71 -> 0 | R78: =M69*3/R71 -> 0
A79: TRANSPORTE | B79: =L69/B71 -> 0.0075555556 | C79: =L69/C71 -> 0.0073913043 | D79: =L69/D71 -> 0.0072340426 | E79: =L69/E71 -> 0.0070833333 | F79: =L69*2/F71 -> 0.013877551 | G79: =L69*3/G71 -> 0.0204 | H79: =L69*2/H71 -> 0.013333333 | I79: =L69*2/I71 -> 0.013076923 | J79: =L69*2/J71 -> 0.012830189 | K79: =L69*2/K71 -> 0.012592593 | L79: =L69*2/L71 -> 0.012363636 | M79: =L69*3/M71 -> 0.018214286 | N79: =L69*2/N71 -> 0.011929825 | O79: =L69*2/O71 -> 0.011724138 | P79: =L69*2/P71 -> 0.011525424 | Q79: =L69*3/Q71 -> 0.017 | R79: =L69*2/R71 -> 0.010967742
A80: SUBTOTAL | B80: =B52+B73+B74+B75+B76+B77+B78+B79+B69 -> 5.1622222 | C80: =B52+C73+C74+C75+C76+C77+C78+C79+B69 -> 5.1613043 | D80: =B52+D73+D74+D75+D76+D77+D78+D79+B69 -> 5.1604255 | E80: =B52+E73+E74+E75+E76+E77+E78+E79+B69 -> 5.1595833 | F80: =B52+F73+F74+F75+F76+F77+F78+F79+B69 -> 5.1763265 | G80: =B52+G73+G74+G75+G76+G77+G78+G79+B69 -> 5.3924 | H80: =B52+H73+H74+H75+H76+H77+H78+H79+B69 -> 5.1741176 | I80: =B52+I73+I74+I75+I76+I77+I78+I79+B69 -> 5.1730769 | J80: =B52+J73+J74+J75+J76+J77+J78+J79+B69 -> 5.1818868 | K80: =B52+K73+K74+K75+K76+K77+K78+K79+B69 -> 5.1807407 | L80: =B52+L73+L74+L75+L76+L77+L78+L79+B69 -> 5.1796364 | M80: =B52+M73+M74+M75+M76+M77+M78+M79+B69 -> 5.3632143 | N80: =B52+N73+N74+N75+N76+N77+N78+N79+B69 -> 5.1866667 | O80: =B52+O73+O74+O75+O76+O77+O78+O79+B69 -> 5.1855172 | P80: =B52+P73+P74+P75+P76+P77+P78+P79+B69 -> 5.1844068 | Q80: =B52+Q73+Q74+Q75+Q76+Q77+Q78+Q79+B69 -> 6.24325 | R80: =B52+R73+R74+R75+R76+R77+R78+R79+B69 -> 5.1896774
A81: MERMA 8%
A82: MERMA 5% | B82: =B80*5% -> 0.25811111 | C82: =C80*5% -> 0.25806522 | D82: =D80*5% -> 0.25802128 | E82: =E80*5% -> 0.25797917 | F82: =F80*5% -> 0.25881633 | G82: =G80*5% -> 0.26962 | H82: =H80*5% -> 0.25870588 | I82: =I80*5% -> 0.25865385 | ... R82: =R80*5% -> 0.25948387
A83: TOTAL 1 | B83: =(B80+B81) -> 5.1622222 | C83: =(C80+C81) -> 5.1613043 | D83: =(D80+D81) -> 5.1604255 | E83: =(E80+E82) -> 5.4175625 | F83: =(F80+F82) -> 5.4351429 | G83: =G80+G82 -> 5.66202 | H83: =H80+H82 -> 5.4328235 | I83: =I80+I82 -> 5.4317308 | J83: =J80+J82 -> 5.4409811 | K83: =K80+K82 -> 5.4397778 | L83: =L80+L82 -> 5.4386182 | M83: =M80+M82 -> 5.631375 | N83: =N80+N82 -> 5.446 | ... R83: =R80+R82 -> 5.4491613
A84: RESIDUOS | B84: =B83*2.5% -> 0.12905556 | C84: =C83*2.5% -> 0.12903261 | D84: =D83*2.5% -> 0.12901064 | E84: =E83*2.5% -> 0.13543906 | F84: =F83*2.5% -> 0.13587857 | G84: =G83*3% -> 0.1698606 | H84: =H83*2.5% -> 0.13582059 | I84: =I83*2.5% -> 0.13579327 | J84: =J83*2.5% -> 0.13602453 | K84: =K83*2.5% -> 0.13599444 | L84: =L83*2.5% -> 0.13596545 | M84: =M83*3% -> 0.16894125 | N84: =N83*2.5% -> 0.13615 | O84: =O83*2.5% -> 0.13611983 | P84: =P83*2.5% -> 0.13609068 | Q84: =Q83*3% -> 0.19666238 | R84: =R83*2.5% -> 0.13622903
A85: TOTAL 2 | B85: =(B83+B84) -> 5.2912778 | C85: =(C83+C84) -> 5.290337 | D85: =(D83+D84) -> 5.2894362 | E85: =(E83+E84) -> 5.5530016 | F85: =(F83+F84) -> 5.5710214 | G85: =(G83+G84) -> 5.8318806 | H85: =(H83+H84) -> 5.5686441 | I85: =(I83+I84) -> 5.567524 | ... R85: =(R83+R84) -> 5.5853903
A88: KG FAB. | B88: 3200 | C88: 3300 | D88: 3400 | E88: 3500 | F88: 3600 | G88: 3700 | H88: 3800 | I88: 3900 | J88: 4000 | K88: 4100 | L88: 4200 | M88: 4300 | N88: 4400 | O88: 4500 | P88: 4600 | Q88: 4700 | R88: 4800
A89: TIEMPO | J89: 850
A90: PRECIO M.O. | B90: =(B89/60)*R69/B88 -> 0 | C90: =(C89/60)*R69/C88 -> 0 | D90: =(D89/60)*R69/D88 -> 0 | E90: =(E89/60)*R69/E88 -> 0 | F90: =(F89/60)*R69/F88 -> 0 | G90: =(G89/60)*R69/G88 -> 0 | H90: =(H89/60)*R69/H88 -> 0 | I90: =(I89/60)*R69/I88 -> 0 | J90: =(J89/60)*R69/J88 -> 0.84645833 | K90: =(K89/60)*R69/K88 -> 0 | L90: =(L89/60)*R69/L88 -> 0 | M90: =(M89/60)*R69/M88 -> 0 | N90: =(N89/60)*R69/N88 -> 0 | O90: =(O89/60)*R69/O88 -> 0 | P90: =(P89/60)*R69/P88 -> 0 | Q90: =(Q89/60)*R69/Q88 -> 0 | R90: =(R89/60)*R69/R88 -> 0
A91: ANALISIS 42€ | B91: =Q69/B88 -> 0 | C91: =Q89/C88 -> 0 | D91: =Q69/D88 -> 0 | E91: =Q69/E88 -> 0 | F91: =Q69/F88 -> 0 | G91: =Q69/G88 -> 0 | H91: =Q69/H88 -> 0 | I91: =Q69/I88 -> 0 | J91: =Q69/J88 -> 0 | K91: =Q69/K88 -> 0 | L91: =Q69/L88 -> 0 | M91: =Q69/M88 -> 0 | N91: =Q69/N88 -> 0 | O91: =Q69/O88 -> 0 | P91: =Q69/P88 -> 0 | Q91: =Q69/Q88 -> 0 | R91: =Q69/R88 -> 0
A92: ANALISIS 68€ | B92: =P69/B88 -> 0 | C92: =P69/C88 -> 0 | D92: =P69/D88 -> 0 | E92: =P69/E88 -> 0 | F92: =P69/F88 -> 0 | G92: =P69/G88 -> 0 | H92: =P69/H88 -> 0 | I92: =P69/I88 -> 0 | J92: =P69/J88 -> 0 | K92: =P69/K88 -> 0 | L92: =P69/L88 -> 0 | M92: =P69/M88 -> 0 | N92: =P69/N88 -> 0 | O92: =P69/O88 -> 0 | P92: =P69/P88 -> 0 | Q92: =P69/Q88 -> 0 | R92: =P69/R88 -> 0
A93: BIDON 100Kg. | B93: =O69*3/B88 -> 0.024375 | C93: =O69*3/C88 -> 0.023636364 | D93: =O69*3/D88 -> 0.022941176 | E93: =O69*3/E88 -> 0.022285714 | F93: =O69*4/F88 -> 0.028888889 | G93: =O69*4/G88 -> 0.028108108 | H93: =O69*4/H88 -> 0.027368421 | I93: =O69*4/I88 -> 0.026666667 | K93: =O69*5/K88 -> 0.031707317 | L93: =O69*5/L88 -> 0.030952381 | M93: =O69*5/M88 -> 0.030232558 | N93: =O69*6/N88 -> 0.035454545 | O93: =O69*6/O88 -> 0.034666667 | P93: =O69*6/P88 -> 0.033913043 | Q93: =O69*6/Q88 -> 0.033191489 | R93: =O69*7/R88 -> 0.037916667
A94: BIDON 1000Kg. | J94: =N69*4/J88 -> 0.21
A95: PALET EURO. | B95: =M69/B88 -> 0 | C95: =M69/C88 -> 0 | D95: =M69/D88 -> 0 | E95: =M69/E88 -> 0 | F95: =M69*2/F88 -> 0 | G95: =M69*2/G88 -> 0 | H95: =M69*2/H88 -> 0 | I95: =M69*2/I88 -> 0 | J95: =M69*2/J88 -> 0 | K95: =M69*2/K88 -> 0 | L95: =M69*2/L88 -> 0 | M95: =M69*2/M88 -> 0 | N95: =M69*2/N88 -> 0 | O95: =M69*2/O88 -> 0 | P95: =M69*2/P88 -> 0 | Q95: =M69*2/Q88 -> 0 | R95: =M69*3/R88 -> 0
A96: TRANSPORTE | B96: =L69/B88 -> 0.0053125 | C96: =L69/C88 -> 0.0051515152 | D96: =L69/D88 -> 0.005 | E96: =L69/E88 -> 0.0048571429 | F96: =L69*2/F88 -> 0.0094444444 | G96: =L69*2/G88 -> 0.0091891892 | H96: =L69*2/H88 -> 0.0089473684 | I96: =L69*2/I88 -> 0.0087179487 | J96: =L69*4/J88 -> 0.017 | K96: =L69*2/K88 -> 0.0082926829 | L96: =L69*2/L88 -> 0.0080952381 | M96: =L69*2/M88 -> 0.0079069767 | N96: =L69*2/N88 -> 0.0077272727 | O96: =L69*2/O88 -> 0.0075555556 | P96: =L69*2/P88 -> 0.0073913043 | Q96: =L69*2/Q88 -> 0.0072340426 | R96: =L69*2/R88 -> 0.0070833333
A97: SUBTOTAL | B97: =B69+B90+B91+B92+B93+B94+B95+B96 -> 5.1496875 | C97: =B69+C90+C91+C92+C93+C94+C95+C96 -> 5.1487879 | D97: =B69+D90+D91+D92+D93+D94+D95+D96 -> 5.1479412 | E97: =B69+E90+E91+E92+E93+E94+E95+E96 -> 5.1471429 | F97: =B69+F90+F91+F92+F93+F94+F95+F96 -> 5.1583333 | G97: =B69+G90+G91+G92+G93+G94+G95+G96 -> 5.1572973 | H97: =B69+H90+H91+H92+H93+H94+H95+H96 -> 5.1563158 | I97: =B69+I90+I91+I92+I93+I94+I95+I96 -> 5.1553846 | J97: =B69+J90+J91+J92+J93+J94+J95+J96 -> 6.1934583 | K97: =B69+K90+K91+K92+K93+K94+K95+K96 -> 5.16 | L97: =B69+L90+L91+L92+L93+L94+L95+L96 -> 5.1590476 | M97: =B69+M90+M91+M92+M93+M94+M95+M96 -> 5.1581395 | N97: =B69+N90+N91+N92+N93+N94+N95+N96 -> 5.1631818 | O97: =B69+O90+O91+O92+O93+O94+O95+O96 -> 5.1622222 | P97: =B69+P90+P91+P92+P93+P94+P95+P96 -> 5.1613043 | Q97: =B69+Q90+Q91+Q92+Q93+Q94+Q95+Q96 -> 5.1604255 | R97: =B69+R90+R91+R92+R93+R94+R95+R96 -> 5.165
A98: MERMA 8%
A99: MERMA 5% | B99: =B97*5% -> 0.25748437 | C99: =C97*5% -> 0.25743939 | D99: =D97*5% -> 0.25739706 | E99: =E97*5% -> 0.25735714 | F99: =F97*5% -> 0.25791667 | G99: =G97*5% -> 0.25786486 | H99: =H97*5% -> 0.25781579 | I99: =I97*5% -> 0.25776923 | ... R99: =R97*5% -> 0.25825
A100: TOTAL 1 | B100: =(B97+B99) -> 5.4071719 | C100: =(C97+C99) -> 5.4062273 | D100: =(D97+D99) -> 5.4053382 | E100: =(E97+E99) -> 5.4045 | F100: =(F97+F99) -> 5.41625 | G100: =G97+G99 -> 5.4151622 | H100: =H97+H99 -> 5.4141316 | I100: =I97+I99 -> 5.4131538 | J100: =J97+J99 -> 6.5031313 | K100: =K97+K99 -> 5.418 | L100: =L97+L99 -> 5.417 | M100: =M97+M99 -> 5.4160465 | N100: =N97+N99 -> 5.4213409 | ... R100: =R97+R99 -> 5.42325
A101: RESIDUOS | B101: =B100*2.5% -> 0.1351793 | C101: =C100*2.5% -> 0.13515568 | D101: =D100*2.5% -> 0.13513346 | E101: =E100*2.5% -> 0.1351125 | F101: =F100*2.5% -> 0.13540625 | G101: =G100*2.5% -> 0.13537905 | H101: =H100*2.5% -> 0.13535329 | I101: =I100*2.5% -> 0.13532885 | J101: =J100*3% -> 0.19509394 | K101: =K100*2.5% -> 0.13545 | L101: =L100*2.5% -> 0.135425 | M101: =M100*2.5% -> 0.13540116 | N101: =N100*2.5% -> 0.13553352 | O101: =O100*2.5% -> 0.13550833 | P101: =P100*2.5% -> 0.13548424 | Q101: =Q100*2.5% -> 0.13546117 | R101: =R100*2.5% -> 0.13558125
A102: TOTAL 2 | B102: =(B100+B101) -> 5.5423512 | C102: =(C100+C101) -> 5.541383 | D102: =(D100+D101) -> 5.5404717 | E102: =(E100+E101) -> 5.5396125 | F102: =(F100+F101) -> 5.5516562 | G102: =(G100+G101) -> 5.5505412 | H102: =(H100+H101) -> 5.5494849 | I102: =(I100+I101) -> 5.5484827 | ... R102: =(R100+R101) -> 5.5588313
A103: M.P | B103: =B69 -> 5.12 | C103: =C1 -> 0 | L103: 10 | N103: 170 | O103: 22 | P103: 68 | Q103: 42 | R103: =R69 -> 239
A105: KG FAB. | B105: 4900 | C105: 5000 | D105: 5100 | E105: 5200 | F105: 5300 | G105: 5400 | H105: 5500 | I105: 5600 | J105: 5700 | K105: 5800 | L105: 5900 | M105: 6000 | N105: 6100 | O105: 6200 | P105: 6300 | Q105: 6400 | R105: 6500
A106: TIEMPO
A107: PRECIO M.O. | B107: =(B106/60)*R103/B105 -> 0 | C107: =(C106/60)*R103/C105 -> 0 | D107: =(D106/60)*R103/D105 -> 0 | E107: =(E106/60)*R103/E105 -> 0 | F107: =(F106/60)*R103/F105 -> 0 | G107: =(G106/60)*R103/G105 -> 0 | H107: =(H106/60)*R103/H105 -> 0 | I107: =(I106/60)*R103/I105 -> 0 | J107: =(J106/60)*R103/J105 -> 0 | K107: =(K106/60)*R103/K105 -> 0 | L107: =(L106/60)*R103/L105 -> 0 | M107: =(M106/60)*R103/M105 -> 0 | N107: =(N106/60)*R103/N105 -> 0 | O107: =(O106/60)*R103/O105 -> 0 | P107: =(P106/60)*R103/P105 -> 0 | Q107: =(Q106/60)*R103/Q105 -> 0 | R107: =(R106/60)*R86/R105 -> 0
A108: ANALISIS 42€ | B108: =Q103/B105 -> 0.0085714286 | C108: =Q103/C105 -> 0.0084 | D108: =Q103/D105 -> 0.0082352941 | E108: =Q103/E105 -> 0.0080769231 | F108: =Q103/F105 -> 0.0079245283 | G108: =Q103/G105 -> 0.0077777778 | H108: =Q103/H105 -> 0.0076363636 | I108: =Q103/I105 -> 0.0075 | J108: =Q103/J105 -> 0.0073684211 | K108: =Q103/K105 -> 0.0072413793 | L108: =Q103/L105 -> 0.0071186441 | M108: =Q103/M105 -> 0.007 | N108: =Q103/N105 -> 0.0068852459 | O108: =Q103/O105 -> 0.0067741935 | P108: =Q103/P105 -> 0.0066666667 | Q108: =Q103/Q105 -> 0.0065625 | R108: =Q103/R105 -> 0.0064615385
A109: ANALISIS 68€ | B109: =P103/B105 -> 0.013877551 | C109: =P103/C105 -> 0.0136 | D109: =P103/D105 -> 0.013333333 | E109: =P103/E105 -> 0.013076923 | F109: =P103/F105 -> 0.012830189 | G109: =P103/G105 -> 0.012592593 | H109: =P103/H105 -> 0.012363636 | I109: =P103/I105 -> 0.012142857 | J109: =P103/J105 -> 0.011929825 | K109: =P103/K105 -> 0.011724138 | L109: =P103/L105 -> 0.011525424 | M109: =P103/M105 -> 0.011333333 | N109: =P103/N105 -> 0.011147541 | O109: =P103/O105 -> 0.010967742 | P109: =P103/P105 -> 0.010793651 | Q109: =P103/Q105 -> 0.010625 | R109: =P103/R105 -> 0.010461538
...

Sheet Gl
A1: Concepto | B1: Definición
A2: Envasado | B2: El cliente aporta el producto a granel; Jumsa solo realiza el envasado.
A3: Bulk | B3: Producción de la fórmula; el cliente se encarga del envasado.
A4: Bulk + envasado | B4: Producción de la fórmula + envasado
A5: Full Service | B5: Servicio completo: fórmula + fabricación + envasado + logística.
A7: Origen MP | B7: Indica quién aporta las materias primas: Cliente, Jumsa o Mixto.
A8: Estado de Fórmula | B8: Clasifica si el producto es nuevo, repetido, actualización de costes o regular.
A9: Cliente aporta MP | B9: El cliente envía las materias primas; reduce precio y margen.
